Workbook

Sheet Read Me
A1: Greenfield Supply Chain Go-Live — End-to-End Tracking Playbook
A2: Companion to the 'AI-Enabled Project Execution for Supply Chain' proposal. One workbook, one source of truth, from initiation to production go-live and close.
A4: HOW TO USE
A5: 1. Stakeholders | B5: Start here. Confirm names, roles and escalation contacts. IDs (SH-xx) are used everywhere else.
A6: 2. Objectives | B6: Charter objectives and success criteria. Every task traces to one objective; objective status rolls up automatically.
A7: 3. Master Plan | B7: The integrated plan and traceability matrix: 81 pre-loaded tasks across 8 phases and 13 workstreams. Update Status, % Complete, Evidence and Notes weekly. Add rows as needed — dropdowns and formulas extend to row 200+.
A8: 4. RACI Matrix | B8: Auto-generated grid of every stakeholder against every task (R/A/C/I), with load totals. Do not edit — change assignments in the Master Plan.
A9: 5. Gate Checklists | B9: Completeness Gate items per phase. A gate shows PASSED only when every item is Complete or N/A. Review before each gate meeting.
A10: 6. RAID Log | B10: Risks, Assumptions, Issues, Dependencies with scoring, owners and due dates. Link each entry to a task.
A11: 7. Action Log | B11: Meeting actions with owners and due dates. Overdue days calculate automatically.
A12: 8. Dashboard | B12: Executive view: overall progress, phase and workstream status, gate status, stakeholder load. Fully formula-driven — nothing to type.
A14: LEGEND
A15: Blue text | B15: Input — type here.
A16: Grey fill | B16: Formula — do not edit.
A17: Yellow fill | B17: Key assumption or field you must set (project name, start date).
A18: Health colours | B18: Green = on track · Amber = at risk / overdue / late start · Red = blocked or > 5 days overdue · Grey = done.
A20: WEEKLY ROUTINE (with AI Copilot)
A21: Monday | B21: Owners update Status / % Complete / Evidence in Master Plan. Copilot flags tasks with no update in 7 days.
A22: Tuesday | B22: PMO reviews Dashboard exceptions only: overdue, at risk, blocked, unowned RAID items, open gate items.
A23: Wednesday | B23: Copilot drafts status report from Dashboard; PM reviews and sends. Meeting actions captured into Action Log.
A24: Gate week | B24: Copilot audits the Gate Checklist and lists gaps; PM confirms; sponsor approves gate at steering committee.
A26: ASSUMPTIONS
A27: Dates | B27: Example plan assumes a 52-week programme starting 05-Oct-2026 (Dashboard B5). All task dates are example inputs — replace with your baseline.
A28: Example data | B28: Rows marked Complete / In Progress in Master Plan, RAID Log and Action Log are illustrative examples showing the expected format.
A29: Phases | B29: Phases follow the five AI Copilot moments (Intake, Plan, Monitor, Communicate, Close) mapped to a greenfield DC lifecycle.

Sheet Dashboard
A1: Greenfield Supply Chain Go-Live — Executive Dashboard
A2: All figures calculate from the tracking sheets. Nothing to edit here except the project name and dates in the blue cells.
A4: Project | B4: Greenfield DC — WMS / WCS / Automation Go-Live
A5: Project start | B5: 46300
A6: Target go-live | B6: =MAX('Master Plan'!L5:L85) -> 46663
A7: Report date | B7: =TODAY() -> 46276
A8: Days to go-live | B8: =B6-B7 -> 387
B10: Total tasks | C10: Complete | D10: % Complete | E10: In progress | F10: At risk / blocked | G10: Overdue tasks | H10: Open RAID items | I10: High-severity RAID | J10: Open actions
B11: =COUNTA('Master Plan'!A5:A185) -> 81 | C11: =COUNTIF('Master Plan'!N5:N185,"Complete") -> 5 | D11: =IF(B11=0,0,C11/B11) -> 0.061728395 | E11: =COUNTIF('Master Plan'!N5:N185,"In Progress") -> 3 | F11: =COUNTIF('Master Plan'!N5:N185,"At Risk")+COUNTIF('Master Plan'!N5:N185,"Blocked") -> 0 | G11: =COUNTIF('Master Plan'!T5:T185,">0") -> 0 | H11: =COUNTIF('RAID Log'!N5:N200,"Open")+COUNTIF('RAID Log'!N5:N200,"In Progress") -> 7 | I11: =COUNTIFS('RAID Log'!K5:K200,"High",'RAID Log'!N5:N200,"Open")+COUNTIFS('RAID Log'!K5:K200,"High",'RAID Log'!N5:N200,"In Progress") -> 2 | J11: =COUNTIF('Action Log'!G5:G200,"Open")+COUNTIF('Action Log'!G5:G200,"In Progress") -> 2
A13: Progress by phase
A14: Phase | B14: Tasks | C14: Complete | D14: % Complete | E14: In Progress | F14: At Risk / Blocked | G14: Overdue | H14: Phase Start | I14: Phase Due | J14: Gate Status
A15: 1. Initiation | B15: =COUNTIF('Master Plan'!B5:B185,A15) -> 7 | C15: 7 | D15: =IF(B15=0,0,C15/B15) -> 1 | E15: 0 | F15: =COUNTIFS('Master Plan'!B5:B185,A15,'Master Plan'!N5:N185,"At Risk")+COUNTIFS('Master Plan'!B5:B185,A15,'Master Plan'!N5:N185,"Blocked") -> 0 | G15: =COUNTIFS('Master Plan'!B5:B185,A15,'Master Plan'!T5:T185,">0") -> 0 | H15: =IF(B15=0,"",SUMPRODUCT(MIN(('Master Plan'!B5:B185=A15)*'Master Plan'!K5:K185+('Master Plan'!B5:B185<>A15)*99999))) -> 46300 | I15: =IF(B15=0,"",SUMPRODUCT(MAX(('Master Plan'!B5:B185=A15)*'Master Plan'!L5:L185))) -> 46327 | J15: ='Gate Checklists'!F5 -> PASSED
A16: 2. Planning & Design | B16: =COUNTIF('Master Plan'!B5:B185,A16) -> 16 | C16: 16 | D16: =IF(B16=0,0,C16/B16) -> 1 | E16: 0 | F16: =COUNTIFS('Master Plan'!B5:B185,A16,'Master Plan'!N5:N185,"At Risk")+COUNTIFS('Master Plan'!B5:B185,A16,'Master Plan'!N5:N185,"Blocked") -> 0 | G16: =COUNTIFS('Master Plan'!B5:B185,A16,'Master Plan'!T5:T185,">0") -> 0 | H16: =IF(B16=0,"",SUMPRODUCT(MIN(('Master Plan'!B5:B185=A16)*'Master Plan'!K5:K185+('Master Plan'!B5:B185<>A16)*99999))) -> 46321 | I16: =IF(B16=0,"",SUMPRODUCT(MAX(('Master Plan'!B5:B185=A16)*'Master Plan'!L5:L185))) -> 46383 | J16: PASSED
A17: 3. Build & Configure | B17: =COUNTIF('Master Plan'!B5:B185,A17) -> 17 | C17: 17 | D17: =IF(B17=0,0,C17/B17) -> 1 | E17: =COUNTIFS('Master Plan'!B5:B185,A17,'Master Plan'!N5:N185,"In Progress") -> 0 | F17: =COUNTIFS('Master Plan'!B5:B185,A17,'Master Plan'!N5:N185,"At Risk")+COUNTIFS('Master Plan'!B5:B185,A17,'Master Plan'!N5:N185,"Blocked") -> 0 | G17: =COUNTIFS('Master Plan'!B5:B185,A17,'Master Plan'!T5:T185,">0") -> 0 | H17: =IF(B17=0,"",SUMPRODUCT(MIN(('Master Plan'!B5:B185=A17)*'Master Plan'!K5:K185+('Master Plan'!B5:B185<>A17)*99999))) -> 46384 | I17: =IF(B17=0,"",SUMPRODUCT(MAX(('Master Plan'!B5:B185=A17)*'Master Plan'!L5:L185))) -> 46481 | J17: PASSED
A18: 4. Site Readiness | B18: =COUNTIF('Master Plan'!B5:B185,A18) -> 9 | C18: 9 | D18: =IF(B18=0,0,C18/B18) -> 1 | E18: =COUNTIFS('Master Plan'!B5:B185,A18,'Master Plan'!N5:N185,"In Progress") -> 0 | F18: =COUNTIFS('Master Plan'!B5:B185,A18,'Master Plan'!N5:N185,"At Risk")+COUNTIFS('Master Plan'!B5:B185,A18,'Master Plan'!N5:N185,"Blocked") -> 0 | G18: =COUNTIFS('Master Plan'!B5:B185,A18,'Master Plan'!T5:T185,">0") -> 0 | H18: =IF(B18=0,"",SUMPRODUCT(MIN(('Master Plan'!B5:B185=A18)*'Master Plan'!K5:K185+('Master Plan'!B5:B185<>A18)*99999))) -> 46468 | I18: =IF(B18=0,"",SUMPRODUCT(MAX(('Master Plan'!B5:B185=A18)*'Master Plan'!L5:L185))) -> 46544 | J18: PASSED
A19: 5. Integration & Testing | B19: =COUNTIF('Master Plan'!B5:B185,A19) -> 9 | C19: 9 | D19: =IF(B19=0,0,C19/B19) -> 1 | E19: =COUNTIFS('Master Plan'!B5:B185,A19,'Master Plan'!N5:N185,"In Progress") -> 0 | F19: =COUNTIFS('Master Plan'!B5:B185,A19,'Master Plan'!N5:N185,"At Risk")+COUNTIFS('Master Plan'!B5:B185,A19,'Master Plan'!N5:N185,"Blocked") -> 0 | G19: =COUNTIFS('Master Plan'!B5:B185,A19,'Master Plan'!T5:T185,">0") -> 0 | H19: =IF(B19=0,"",SUMPRODUCT(MIN(('Master Plan'!B5:B185=A19)*'Master Plan'!K5:K185+('Master Plan'!B5:B185<>A19)*99999))) -> 46482 | I19: =IF(B19=0,"",SUMPRODUCT(MAX(('Master Plan'!B5:B185=A19)*'Master Plan'!L5:L185))) -> 46579 | J19: PASSED
A20: 6. Training & Change | B20: =COUNTIF('Master Plan'!B5:B185,A20) -> 7 | C20: 7 | D20: =IF(B20=0,0,C20/B20) -> 1 | E20: =COUNTIFS('Master Plan'!B5:B185,A20,'Master Plan'!N5:N185,"In Progress") -> 0 | F20: =COUNTIFS('Master Plan'!B5:B185,A20,'Master Plan'!N5:N185,"At Risk")+COUNTIFS('Master Plan'!B5:B185,A20,'Master Plan'!N5:N185,"Blocked") -> 0 | G20: =COUNTIFS('Master Plan'!B5:B185,A20,'Master Plan'!T5:T185,">0") -> 0 | H20: =IF(B20=0,"",SUMPRODUCT(MIN(('Master Plan'!B5:B185=A20)*'Master Plan'!K5:K185+('Master Plan'!B5:B185<>A20)*99999))) -> 46510 | I20: =IF(B20=0,"",SUMPRODUCT(MAX(('Master Plan'!B5:B185=A20)*'Master Plan'!L5:L185))) -> 46593 | J20: PASSED
A21: 7. Cutover & Go-Live | B21: =COUNTIF('Master Plan'!B5:B185,A21) -> 9 | C21: 9 | D21: =IF(B21=0,0,C21/B21) -> 1 | E21: =COUNTIFS('Master Plan'!B5:B185,A21,'Master Plan'!N5:N185,"In Progress") -> 0 | F21: =COUNTIFS('Master Plan'!B5:B185,A21,'Master Plan'!N5:N185,"At Risk")+COUNTIFS('Master Plan'!B5:B185,A21,'Master Plan'!N5:N185,"Blocked") -> 0 | G21: =COUNTIFS('Master Plan'!B5:B185,A21,'Master Plan'!T5:T185,">0") -> 0 | H21: =IF(B21=0,"",SUMPRODUCT(MIN(('Master Plan'!B5:B185=A21)*'Master Plan'!K5:K185+('Master Plan'!B5:B185<>A21)*99999))) -> 46566 | I21: =IF(B21=0,"",SUMPRODUCT(MAX(('Master Plan'!B5:B185=A21)*'Master Plan'!L5:L185))) -> 46614 | J21: PASSED
A22: 8. Hypercare & Close | B22: =COUNTIF('Master Plan'!B5:B185,A22) -> 7 | C22: =COUNTIFS('Master Plan'!B5:B185,A22,'Master Plan'!N5:N185,"Complete") -> 0 | D22: =IF(B22=0,0,C22/B22) -> 0 | E22: =COUNTIFS('Master Plan'!B5:B185,A22,'Master Plan'!N5:N185,"In Progress") -> 0 | F22: =COUNTIFS('Master Plan'!B5:B185,A22,'Master Plan'!N5:N185,"At Risk")+COUNTIFS('Master Plan'!B5:B185,A22,'Master Plan'!N5:N185,"Blocked") -> 0 | G22: =COUNTIFS('Master Plan'!B5:B185,A22,'Master Plan'!T5:T185,">0") -> 0 | H22: =IF(B22=0,"",SUMPRODUCT(MIN(('Master Plan'!B5:B185=A22)*'Master Plan'!K5:K185+('Master Plan'!B5:B185<>A22)*99999))) -> 46608 | I22: =IF(B22=0,"",SUMPRODUCT(MAX(('Master Plan'!B5:B185=A22)*'Master Plan'!L5:L185))) -> 46663 | J22: ='Gate Checklists'!F67 -> OPEN — 7 item(s)
A23: Total | B23: =SUM(B15:B22) -> 81 | C23: =SUM(C15:C22) -> 74 | D23: =IF(B23=0,0,C23/B23) -> 0.91358025 | E23: =SUM(E15:E22) -> 0 | F23: =SUM(F15:F22) -> 0 | G23: =SUM(G15:G22) -> 0
A25: Workload by workstream
A26: Workstream | B26: Tasks | C26: Complete | D26: % Complete | E26: In Progress | F26: At Risk / Blocked | G26: Overdue
A27: Automation (MHE) | B27: =COUNTIF('Master Plan'!C5:C185,A27) -> 6 | C27: 5 | D27: =IF(B27=0,0,C27/B27) -> 0.83333333 | E27: =COUNTIFS('Master Plan'!C5:C185,A27,'Master Plan'!N5:N185,"In Progress") -> 0 | F27: =COUNTIFS('Master Plan'!C5:C185,A27,'Master Plan'!N5:N185,"At Risk")+COUNTIFS('Master Plan'!C5:C185,A27,'Master Plan'!N5:N185,"Blocked") -> 0 | G27: =COUNTIFS('Master Plan'!C5:C185,A27,'Master Plan'!T5:T185,">0") -> 0
A28: Change & Training | B28: =COUNTIF('Master Plan'!C5:C185,A28) -> 5 | C28: =COUNTIFS('Master Plan'!C5:C185,A28,'Master Plan'!N5:N185,"Complete") -> 0 | D28: =IF(B28=0,0,C28/B28) -> 0 | E28: =COUNTIFS('Master Plan'!C5:C185,A28,'Master Plan'!N5:N185,"In Progress") -> 0 | F28: =COUNTIFS('Master Plan'!C5:C185,A28,'Master Plan'!N5:N185,"At Risk")+COUNTIFS('Master Plan'!C5:C185,A28,'Master Plan'!N5:N185,"Blocked") -> 0 | G28: =COUNTIFS('Master Plan'!C5:C185,A28,'Master Plan'!T5:T185,">0") -> 0
A29: Cutover & Go-Live | B29: =COUNTIF('Master Plan'!C5:C185,A29) -> 4 | C29: =COUNTIFS('Master Plan'!C5:C185,A29,'Master Plan'!N5:N185,"Complete") -> 0 | D29: =IF(B29=0,0,C29/B29) -> 0 | E29: =COUNTIFS('Master Plan'!C5:C185,A29,'Master Plan'!N5:N185,"In Progress") -> 0 | F29: =COUNTIFS('Master Plan'!C5:C185,A29,'Master Plan'!N5:N185,"At Risk")+COUNTIFS('Master Plan'!C5:C185,A29,'Master Plan'!N5:N185,"Blocked") -> 0 | G29: =COUNTIFS('Master Plan'!C5:C185,A29,'Master Plan'!T5:T185,">0") -> 0
A30: Finance | B30: =COUNTIF('Master Plan'!C5:C185,A30) -> 3 | C30: 2 | D30: =IF(B30=0,0,C30/B30) -> 0.66666667 | E30: =COUNTIFS('Master Plan'!C5:C185,A30,'Master Plan'!N5:N185,"In Progress") -> 0 | F30: =COUNTIFS('Master Plan'!C5:C185,A30,'Master Plan'!N5:N185,"At Risk")+COUNTIFS('Master Plan'!C5:C185,A30,'Master Plan'!N5:N185,"Blocked") -> 0 | G30: =COUNTIFS('Master Plan'!C5:C185,A30,'Master Plan'!T5:T185,">0") -> 0
A31: Hypercare & Close | B31: =COUNTIF('Master Plan'!C5:C185,A31) -> 3 | C31: =COUNTIFS('Master Plan'!C5:C185,A31,'Master Plan'!N5:N185,"Complete") -> 0 | D31: =IF(B31=0,0,C31/B31) -> 0 | E31: =COUNTIFS('Master Plan'!C5:C185,A31,'Master Plan'!N5:N185,"In Progress") -> 0 | F31: =COUNTIFS('Master Plan'!C5:C185,A31,'Master Plan'!N5:N185,"At Risk")+COUNTIFS('Master Plan'!C5:C185,A31,'Master Plan'!N5:N185,"Blocked") -> 0 | G31: =COUNTIFS('Master Plan'!C5:C185,A31,'Master Plan'!T5:T185,">0") -> 0
A32: Infrastructure | B32: =COUNTIF('Master Plan'!C5:C185,A32) -> 3 | C32: =COUNTIFS('Master Plan'!C5:C185,A32,'Master Plan'!N5:N185,"Complete") -> 0 | D32: =IF(B32=0,0,C32/B32) -> 0 | E32: =COUNTIFS('Master Plan'!C5:C185,A32,'Master Plan'!N5:N185,"In Progress") -> 0 | F32: =COUNTIFS('Master Plan'!C5:C185,A32,'Master Plan'!N5:N185,"At Risk")+COUNTIFS('Master Plan'!C5:C185,A32,'Master Plan'!N5:N185,"Blocked") -> 0 | G32: =COUNTIFS('Master Plan'!C5:C185,A32,'Master Plan'!T5:T185,">0") -> 0
A33: Integration & Data | B33: =COUNTIF('Master Plan'!C5:C185,A33) -> 9 | C33: =COUNTIFS('Master Plan'!C5:C185,A33,'Master Plan'!N5:N185,"Complete") -> 0 | D33: =IF(B33=0,0,C33/B33) -> 0 | E33: =COUNTIFS('Master Plan'!C5:C185,A33,'Master Plan'!N5:N185,"In Progress") -> 0 | F33: =COUNTIFS('Master Plan'!C5:C185,A33,'Master Plan'!N5:N185,"At Risk")+COUNTIFS('Master Plan'!C5:C185,A33,'Master Plan'!N5:N185,"Blocked") -> 0 | G33: =COUNTIFS('Master Plan'!C5:C185,A33,'Master Plan'!T5:T185,">0") -> 0
A34: Operations & Staffing | B34: =COUNTIF('Master Plan'!C5:C185,A34) -> 8 | C34: =COUNTIFS('Master Plan'!C5:C185,A34,'Master Plan'!N5:N185,"Complete") -> 0 | D34: =IF(B34=0,0,C34/B34) -> 0 | E34: =COUNTIFS('Master Plan'!C5:C185,A34,'Master Plan'!N5:N185,"In Progress") -> 0 | F34: =COUNTIFS('Master Plan'!C5:C185,A34,'Master Plan'!N5:N185,"At Risk")+COUNTIFS('Master Plan'!C5:C185,A34,'Master Plan'!N5:N185,"Blocked") -> 0 | G34: =COUNTIFS('Master Plan'!C5:C185,A34,'Master Plan'!T5:T185,">0") -> 0
A35: PMO | B35: =COUNTIF('Master Plan'!C5:C185,A35) -> 16 | C35: 10 | D35: =IF(B35=0,0,C35/B35) -> 0.625 | E35: =COUNTIFS('Master Plan'!C5:C185,A35,'Master Plan'!N5:N185,"In Progress") -> 2 | F35: =COUNTIFS('Master Plan'!C5:C185,A35,'Master Plan'!N5:N185,"At Risk")+COUNTIFS('Master Plan'!C5:C185,A35,'Master Plan'!N5:N185,"Blocked") -> 0 | G35: =COUNTIFS('Master Plan'!C5:C185,A35,'Master Plan'!T5:T185,">0") -> 0
A36: Safety & Compliance | B36: =COUNTIF('Master Plan'!C5:C185,A36) -> 2 | C36: =COUNTIFS('Master Plan'!C5:C185,A36,'Master Plan'!N5:N185,"Complete") -> 0 | D36: =IF(B36=0,0,C36/B36) -> 0 | E36: =COUNTIFS('Master Plan'!C5:C185,A36,'Master Plan'!N5:N185,"In Progress") -> 0 | F36: =COUNTIFS('Master Plan'!C5:C185,A36,'Master Plan'!N5:N185,"At Risk")+COUNTIFS('Master Plan'!C5:C185,A36,'Master Plan'!N5:N185,"Blocked") -> 0 | G36: =COUNTIFS('Master Plan'!C5:C185,A36,'Master Plan'!T5:T185,">0") -> 0
A37: Site Readiness | B37: =COUNTIF('Master Plan'!C5:C185,A37) -> 4 | C37: =COUNTIFS('Master Plan'!C5:C185,A37,'Master Plan'!N5:N185,"Complete") -> 0 | D37: =IF(B37=0,0,C37/B37) -> 0 | E37: =COUNTIFS('Master Plan'!C5:C185,A37,'Master Plan'!N5:N185,"In Progress") -> 0 | F37: =COUNTIFS('Master Plan'!C5:C185,A37,'Master Plan'!N5:N185,"At Risk")+COUNTIFS('Master Plan'!C5:C185,A37,'Master Plan'!N5:N185,"Blocked") -> 0 | G37: =COUNTIFS('Master Plan'!C5:C185,A37,'Master Plan'!T5:T185,">0") -> 0
A38: Sponsor | B38: =COUNTIF('Master Plan'!C5:C185,A38) -> 0 | C38: =COUNTIFS('Master Plan'!C5:C185,A38,'Master Plan'!N5:N185,"Complete") -> 0 | D38: =IF(B38=0,0,C38/B38) -> 0 | E38: =COUNTIFS('Master Plan'!C5:C185,A38,'Master Plan'!N5:N185,"In Progress") -> 0 | F38: =COUNTIFS('Master Plan'!C5:C185,A38,'Master Plan'!N5:N185,"At Risk")+COUNTIFS('Master Plan'!C5:C185,A38,'Master Plan'!N5:N185,"Blocked") -> 0 | G38: =COUNTIFS('Master Plan'!C5:C185,A38,'Master Plan'!T5:T185,">0") -> 0
A39: Testing | B39: =COUNTIF('Master Plan'!C5:C185,A39) -> 5 | C39: =COUNTIFS('Master Plan'!C5:C185,A39,'Master Plan'!N5:N185,"Complete") -> 0 | D39: =IF(B39=0,0,C39/B39) -> 0 | E39: =COUNTIFS('Master Plan'!C5:C185,A39,'Master Plan'!N5:N185,"In Progress") -> 0 | F39: =COUNTIFS('Master Plan'!C5:C185,A39,'Master Plan'!N5:N185,"At Risk")+COUNTIFS('Master Plan'!C5:C185,A39,'Master Plan'!N5:N185,"Blocked") -> 0 | G39: =COUNTIFS('Master Plan'!C5:C185,A39,'Master Plan'!T5:T185,">0") -> 0
A40: Transportation | B40: =COUNTIF('Master Plan'!C5:C185,A40) -> 4 | C40: =COUNTIFS('Master Plan'!C5:C185,A40,'Master Plan'!N5:N185,"Complete") -> 0 | D40: =IF(B40=0,0,C40/B40) -> 0 | E40: =COUNTIFS('Master Plan'!C5:C185,A40,'Master Plan'!N5:N185,"In Progress") -> 0 | F40: =COUNTIFS('Master Plan'!C5:C185,A40,'Master Plan'!N5:N185,"At Risk")+COUNTIFS('Master Plan'!C5:C185,A40,'Master Plan'!N5:N185,"Blocked") -> 0 | G40: =COUNTIFS('Master Plan'!C5:C185,A40,'Master Plan'!T5:T185,">0") -> 0
A41: Vendors | B41: =COUNTIF('Master Plan'!C5:C185,A41) -> 3 | C41: =COUNTIFS('Master Plan'!C5:C185,A41,'Master Plan'!N5:N185,"Complete") -> 0 | D41: =IF(B41=0,0,C41/B41) -> 0 | E41: =COUNTIFS('Master Plan'!C5:C185,A41,'Master Plan'!N5:N185,"In Progress") -> 1 | F41: =COUNTIFS('Master Plan'!C5:C185,A41,'Master Plan'!N5:N185,"At Risk")+COUNTIFS('Master Plan'!C5:C185,A41,'Master Plan'!N5:N185,"Blocked") -> 0 | G41: =COUNTIFS('Master Plan'!C5:C185,A41,'Master Plan'!T5:T185,">0") -> 0
A42: WMS / WCS | B42: =COUNTIF('Master Plan'!C5:C185,A42) -> 6 | C42: 6 | D42: =IF(B42=0,0,C42/B42) -> 1 | E42: =COUNTIFS('Master Plan'!C5:C185,A42,'Master Plan'!N5:N185,"In Progress") -> 0 | F42: =COUNTIFS('Master Plan'!C5:C185,A42,'Master Plan'!N5:N185,"At Risk")+COUNTIFS('Master Plan'!C5:C185,A42,'Master Plan'!N5:N185,"Blocked") -> 0 | G42: =COUNTIFS('Master Plan'!C5:C185,A42,'Master Plan'!T5:T185,">0") -> 0
A45: Stakeholder assignments (Responsible)
A46: Stakeholder | B46: Responsible for | C46: Accountable for | D46: Open (R) | E46: Overdue (R) | F46: Open RAID owned | G46: Open actions owned
A47: =Stakeholders!B5 -> Executive Sponsor | B47: =COUNTIF('Master Plan'!G5:G185,Stakeholders!A5) -> 1 | C47: =COUNTIF('Master Plan'!H5:H185,Stakeholders!A5) -> 15 | D47: =B47-COUNTIFS('Master Plan'!G5:G185,Stakeholders!A5,'Master Plan'!N5:N185,"Complete") -> 0 | E47: =COUNTIFS('Master Plan'!G5:G185,Stakeholders!A5,'Master Plan'!T5:T185,">0") -> 0 | F47: =COUNTIFS('RAID Log'!F5:F200,Stakeholders!A5,'RAID Log'!N5:N200,"Open")+COUNTIFS('RAID Log'!F5:F200,Stakeholders!A5,'RAID Log'!N5:N200,"In Progress") -> 0 | G47: =COUNTIFS('Action Log'!D5:D200,Stakeholders!A5,'Action Log'!G5:G200,"Open")+COUNTIFS('Action Log'!D5:D200,Stakeholders!A5,'Action Log'!G5:G200,"In Progress") -> 0
A48: =Stakeholders!B6 -> Program Manager | B48: =COUNTIF('Master Plan'!G5:G185,Stakeholders!A6) -> 14 | C48: =COUNTIF('Master Plan'!H5:H185,Stakeholders!A6) -> 7 | D48: =B48-COUNTIFS('Master Plan'!G5:G185,Stakeholders!A6,'Master Plan'!N5:N185,"Complete") -> 11 | E48: =COUNTIFS('Master Plan'!G5:G185,Stakeholders!A6,'Master Plan'!T5:T185,">0") -> 0 | F48: =COUNTIFS('RAID Log'!F5:F200,Stakeholders!A6,'RAID Log'!N5:N200,"Open")+COUNTIFS('RAID Log'!F5:F200,Stakeholders!A6,'RAID Log'!N5:N200,"In Progress") -> 0 | G48: =COUNTIFS('Action Log'!D5:D200,Stakeholders!A6,'Action Log'!G5:G200,"Open")+COUNTIFS('Action Log'!D5:D200,Stakeholders!A6,'Action Log'!G5:G200,"In Progress") -> 0
A49: =Stakeholders!B7 -> PMO Analyst | B49: =COUNTIF('Master Plan'!G5:G185,Stakeholders!A7) -> 1 | C49: =COUNTIF('Master Plan'!H5:H185,Stakeholders!A7) -> 0 | D49: =B49-COUNTIFS('Master Plan'!G5:G185,Stakeholders!A7,'Master Plan'!N5:N185,"Complete") -> 1 | E49: =COUNTIFS('Master Plan'!G5:G185,Stakeholders!A7,'Master Plan'!T5:T185,">0") -> 0 | F49: =COUNTIFS('RAID Log'!F5:F200,Stakeholders!A7,'RAID Log'!N5:N200,"Open")+COUNTIFS('RAID Log'!F5:F200,Stakeholders!A7,'RAID Log'!N5:N200,"In Progress") -> 0 | G49: =COUNTIFS('Action Log'!D5:D200,Stakeholders!A7,'Action Log'!G5:G200,"Open")+COUNTIFS('Action Log'!D5:D200,Stakeholders!A7,'Action Log'!G5:G200,"In Progress") -> 0
A50: =Stakeholders!B8 -> Site / Facilities Lead | B50: =COUNTIF('Master Plan'!G5:G185,Stakeholders!A8) -> 5 | C50: =COUNTIF('Master Plan'!H5:H185,Stakeholders!A8) -> 4 | D50: =B50-COUNTIFS('Master Plan'!G5:G185,Stakeholders!A8,'Master Plan'!N5:N185,"Complete") -> 5 | E50: =COUNTIFS('Master Plan'!G5:G185,Stakeholders!A8,'Master Plan'!T5:T185,">0") -> 0 | F50: =COUNTIFS('RAID Log'!F5:F200,Stakeholders!A8,'RAID Log'!N5:N200,"Open")+COUNTIFS('RAID Log'!F5:F200,Stakeholders!A8,'RAID Log'!N5:N200,"In Progress") -> 1 | G50: =COUNTIFS('Action Log'!D5:D200,Stakeholders!A8,'Action Log'!G5:G200,"Open")+COUNTIFS('Action Log'!D5:D200,Stakeholders!A8,'Action Log'!G5:G200,"In Progress") -> 0
A51: =Stakeholders!B9 -> WMS Product Owner | B51: =COUNTIF('Master Plan'!G5:G185,Stakeholders!A9) -> 1 | C51: =COUNTIF('Master Plan'!H5:H185,Stakeholders!A9) -> 7 | D51: =B51-COUNTIFS('Master Plan'!G5:G185,Stakeholders!A9,'Master Plan'!N5:N185,"Complete") -> 1 | E51: =COUNTIFS('Master Plan'!G5:G185,Stakeholders!A9,'Master Plan'!T5:T185,">0") -> 0 | F51: =COUNTIFS('RAID Log'!F5:F200,Stakeholders!A9,'RAID Log'!N5:N200,"Open")+COUNTIFS('RAID Log'!F5:F200,Stakeholders!A9,'RAID Log'!N5:N200,"In Progress") -> 0 | G51: =COUNTIFS('Action Log'!D5:D200,Stakeholders!A9,'Action Log'!G5:G200,"Open")+COUNTIFS('Action Log'!D5:D200,Stakeholders!A9,'Action Log'!G5:G200,"In Progress") -> 0
A52: =Stakeholders!B10 -> WMS Tech Lead | B52: =COUNTIF('Master Plan'!G5:G185,Stakeholders!A10) -> 5 | C52: =COUNTIF('Master Plan'!H5:H185,Stakeholders!A10) -> 1 | D52: =B52-COUNTIFS('Master Plan'!G5:G185,Stakeholders!A10,'Master Plan'!N5:N185,"Complete") -> 5 | E52: =COUNTIFS('Master Plan'!G5:G185,Stakeholders!A10,'Master Plan'!T5:T185,">0") -> 0 | F52: =COUNTIFS('RAID Log'!F5:F200,Stakeholders!A10,'RAID Log'!N5:N200,"Open")+COUNTIFS('RAID Log'!F5:F200,Stakeholders!A10,'RAID Log'!N5:N200,"In Progress") -> 0 | G52: =COUNTIFS('Action Log'!D5:D200,Stakeholders!A10,'Action Log'!G5:G200,"Open")+COUNTIFS('Action Log'!D5:D200,Stakeholders!A10,'Action Log'!G5:G200,"In Progress") -> 0
A53: =Stakeholders!B11 -> WCS / Automation Lead | B53: =COUNTIF('Master Plan'!G5:G185,Stakeholders!A11) -> 2 | C53: =COUNTIF('Master Plan'!H5:H185,Stakeholders!A11) -> 7 | D53: =B53-COUNTIFS('Master Plan'!G5:G185,Stakeholders!A11,'Master Plan'!N5:N185,"Complete") -> 2 | E53: =COUNTIFS('Master Plan'!G5:G185,Stakeholders!A11,'Master Plan'!T5:T185,">0") -> 0 | F53: =COUNTIFS('RAID Log'!F5:F200,Stakeholders!A11,'RAID Log'!N5:N200,"Open")+COUNTIFS('RAID Log'!F5:F200,Stakeholders!A11,'RAID Log'!N5:N200,"In Progress") -> 1 | G53: =COUNTIFS('Action Log'!D5:D200,Stakeholders!A11,'Action Log'!G5:G200,"Open")+COUNTIFS('Action Log'!D5:D200,Stakeholders!A11,'Action Log'!G5:G200,"In Progress") -> 0
A54: =Stakeholders!B12 -> Integration / ERP Lead | B54: =COUNTIF('Master Plan'!G5:G185,Stakeholders!A12) -> 4 | C54: =COUNTIF('Master Plan'!H5:H185,Stakeholders!A12) -> 8 | D54: =B54-COUNTIFS('Master Plan'!G5:G185,Stakeholders!A12,'Master Plan'!N5:N185,"Complete") -> 4 | E54: =COUNTIFS('Master Plan'!G5:G185,Stakeholders!A12,'Master Plan'!T5:T185,">0") -> 0 | F54: =COUNTIFS('RAID Log'!F5:F200,Stakeholders!A12,'RAID Log'!N5:N200,"Open")+COUNTIFS('RAID Log'!F5:F200,Stakeholders!A12,'RAID Log'!N5:N200,"In Progress") -> 1 | G54: =COUNTIFS('Action Log'!D5:D200,Stakeholders!A12,'Action Log'!G5:G200,"Open")+COUNTIFS('Action Log'!D5:D200,Stakeholders!A12,'Action Log'!G5:G200,"In Progress") -> 0
A55: =Stakeholders!B13 -> Data Migration Lead | B55: =COUNTIF('Master Plan'!G5:G185,Stakeholders!A13) -> 5 | C55: =COUNTIF('Master Plan'!H5:H185,Stakeholders!A13) -> 1 | D55: =B55-COUNTIFS('Master Plan'!G5:G185,Stakeholders!A13,'Master Plan'!N5:N185,"Complete") -> 5 | E55: =COUNTIFS('Master Plan'!G5:G185,Stakeholders!A13,'Master Plan'!T5:T185,">0") -> 0 | F55: =COUNTIFS('RAID Log'!F5:F200,Stakeholders!A13,'RAID Log'!N5:N200,"Open")+COUNTIFS('RAID Log'!F5:F200,Stakeholders!A13,'RAID Log'!N5:N200,"In Progress") -> 0 | G55: =COUNTIFS('Action Log'!D5:D200,Stakeholders!A13,'Action Log'!G5:G200,"Open")+COUNTIFS('Action Log'!D5:D200,Stakeholders!A13,'Action Log'!G5:G200,"In Progress") -> 0
A56: =Stakeholders!B14 -> QA / Test Manager | B56: =COUNTIF('Master Plan'!G5:G185,Stakeholders!A14) -> 4 | C56: =COUNTIF('Master Plan'!H5:H185,Stakeholders!A14) -> 2 | D56: =B56-COUNTIFS('Master Plan'!G5:G185,Stakeholders!A14,'Master Plan'!N5:N185,"Complete") -> 4 | E56: =COUNTIFS('Master Plan'!G5:G185,Stakeholders!A14,'Master Plan'!T5:T185,">0") -> 0 | F56: =COUNTIFS('RAID Log'!F5:F200,Stakeholders!A14,'RAID Log'!N5:N200,"Open")+COUNTIFS('RAID Log'!F5:F200,Stakeholders!A14,'RAID Log'!N5:N200,"In Progress") -> 1 | G56: =COUNTIFS('Action Log'!D5:D200,Stakeholders!A14,'Action Log'!G5:G200,"Open")+COUNTIFS('Action Log'!D5:D200,Stakeholders!A14,'Action Log'!G5:G200,"In Progress") -> 0
A57: =Stakeholders!B15 -> Operations Lead | B57: =COUNTIF('Master Plan'!G5:G185,Stakeholders!A15) -> 10 | C57: =COUNTIF('Master Plan'!H5:H185,Stakeholders!A15) -> 11 | D57: =B57-COUNTIFS('Master Plan'!G5:G185,Stakeholders!A15,'Master Plan'!N5:N185,"Complete") -> 10 | E57: =COUNTIFS('Master Plan'!G5:G185,Stakeholders!A15,'Master Plan'!T5:T185,">0") -> 0 | F57: =COUNTIFS('RAID Log'!F5:F200,Stakeholders!A15,'RAID Log'!N5:N200,"Open")+COUNTIFS('RAID Log'!F5:F200,Stakeholders!A15,'RAID Log'!N5:N200,"In Progress") -> 1 | G57: =COUNTIFS('Action Log'!D5:D200,Stakeholders!A15,'Action Log'!G5:G200,"Open")+COUNTIFS('Action Log'!D5:D200,Stakeholders!A15,'Action Log'!G5:G200,"In Progress") -> 0
A58: =Stakeholders!B16 -> Transportation Lead | B58: =COUNTIF('Master Plan'!G5:G185,Stakeholders!A16) -> 4 | C58: =COUNTIF('Master Plan'!H5:H185,Stakeholders!A16) -> 4 | D58: =B58-COUNTIFS('Master Plan'!G5:G185,Stakeholders!A16,'Master Plan'!N5:N185,"Complete") -> 4 | E58: =COUNTIFS('Master Plan'!G5:G185,Stakeholders!A16,'Master Plan'!T5:T185,">0") -> 0 | F58: =COUNTIFS('RAID Log'!F5:F200,Stakeholders!A16,'RAID Log'!N5:N200,"Open")+COUNTIFS('RAID Log'!F5:F200,Stakeholders!A16,'RAID Log'!N5:N200,"In Progress") -> 1 | G58: =COUNTIFS('Action Log'!D5:D200,Stakeholders!A16,'Action Log'!G5:G200,"Open")+COUNTIFS('Action Log'!D5:D200,Stakeholders!A16,'Action Log'!G5:G200,"In Progress") -> 0
A59: =Stakeholders!B17 -> Procurement / Vendor Lead | B59: =COUNTIF('Master Plan'!G5:G185,Stakeholders!A17) -> 3 | C59: =COUNTIF('Master Plan'!H5:H185,Stakeholders!A17) -> 1 | D59: =B59-COUNTIFS('Master Plan'!G5:G185,Stakeholders!A17,'Master Plan'!N5:N185,"Complete") -> 3 | E59: =COUNTIFS('Master Plan'!G5:G185,Stakeholders!A17,'Master Plan'!T5:T185,">0") -> 0 | F59: =COUNTIFS('RAID Log'!F5:F200,Stakeholders!A17,'RAID Log'!N5:N200,"Open")+COUNTIFS('RAID Log'!F5:F200,Stakeholders!A17,'RAID Log'!N5:N200,"In Progress") -> 0 | G59: =COUNTIFS('Action Log'!D5:D200,Stakeholders!A17,'Action Log'!G5:G200,"Open")+COUNTIFS('Action Log'!D5:D200,Stakeholders!A17,'Action Log'!G5:G200,"In Progress") -> 1
A60: =Stakeholders!B18 -> MHE Vendor PM | B60: =COUNTIF('Master Plan'!G5:G185,Stakeholders!A18) -> 4 | C60: =COUNTIF('Master Plan'!H5:H185,Stakeholders!A18) -> 0 | D60: =B60-COUNTIFS('Master Plan'!G5:G185,Stakeholders!A18,'Master Plan'!N5:N185,"Complete") -> 4 | E60: =COUNTIFS('Master Plan'!G5:G185,Stakeholders!A18,'Master Plan'!T5:T185,">0") -> 0 | F60: =COUNTIFS('RAID Log'!F5:F200,Stakeholders!A18,'RAID Log'!N5:N200,"Open")+COUNTIFS('RAID Log'!F5:F200,Stakeholders!A18,'RAID Log'!N5:N200,"In Progress") -> 0 | G60: =COUNTIFS('Action Log'!D5:D200,Stakeholders!A18,'Action Log'!G5:G200,"Open")+COUNTIFS('Action Log'!D5:D200,Stakeholders!A18,'Action Log'!G5:G200,"In Progress") -> 0
A61: =Stakeholders!B19 -> Safety & Compliance Lead | B61: =COUNTIF('Master Plan'!G5:G185,Stakeholders!A19) -> 1 | C61: =COUNTIF('Master Plan'!H5:H185,Stakeholders!A19) -> 2 | D61: =B61-COUNTIFS('Master Plan'!G5:G185,Stakeholders!A19,'Master Plan'!N5:N185,"Complete") -> 1 | E61: =COUNTIFS('Master Plan'!G5:G185,Stakeholders!A19,'Master Plan'!T5:T185,">0") -> 0 | F61: =COUNTIFS('RAID Log'!F5:F200,Stakeholders!A19,'RAID Log'!N5:N200,"Open")+COUNTIFS('RAID Log'!F5:F200,Stakeholders!A19,'RAID Log'!N5:N200,"In Progress") -> 0 | G61: =COUNTIFS('Action Log'!D5:D200,Stakeholders!A19,'Action Log'!G5:G200,"Open")+COUNTIFS('Action Log'!D5:D200,Stakeholders!A19,'Action Log'!G5:G200,"In Progress") -> 0
A62: =Stakeholders!B20 -> Finance Partner | B62: =COUNTIF('Master Plan'!G5:G185,Stakeholders!A20) -> 3 | C62: =COUNTIF('Master Plan'!H5:H185,Stakeholders!A20) -> 2 | D62: =B62-COUNTIFS('Master Plan'!G5:G185,Stakeholders!A20,'Master Plan'!N5:N185,"Complete") -> 2 | E62: =COUNTIFS('Master Plan'!G5:G185,Stakeholders!A20,'Master Plan'!T5:T185,">0") -> 0 | F62: =COUNTIFS('RAID Log'!F5:F200,Stakeholders!A20,'RAID Log'!N5:N200,"Open")+COUNTIFS('RAID Log'!F5:F200,Stakeholders!A20,'RAID Log'!N5:N200,"In Progress") -> 0 | G62: =COUNTIFS('Action Log'!D5:D200,Stakeholders!A20,'Action Log'!G5:G200,"Open")+COUNTIFS('Action Log'!D5:D200,Stakeholders!A20,'Action Log'!G5:G200,"In Progress") -> 0
A63: =Stakeholders!B21 -> Change & Training Lead | B63: =COUNTIF('Master Plan'!G5:G185,Stakeholders!A21) -> 5 | C63: =COUNTIF('Master Plan'!H5:H185,Stakeholders!A21) -> 2 | D63: =B63-COUNTIFS('Master Plan'!G5:G185,Stakeholders!A21,'Master Plan'!N5:N185,"Complete") -> 5 | E63: =COUNTIFS('Master Plan'!G5:G185,Stakeholders!A21,'Master Plan'!T5:T185,">0") -> 0 | F63: =COUNTIFS('RAID Log'!F5:F200,Stakeholders!A21,'RAID Log'!N5:N200,"Open")+COUNTIFS('RAID Log'!F5:F200,Stakeholders!A21,'RAID Log'!N5:N200,"In Progress") -> 0 | G63: =COUNTIFS('Action Log'!D5:D200,Stakeholders!A21,'Action Log'!G5:G200,"Open")+COUNTIFS('Action Log'!D5:D200,Stakeholders!A21,'Action Log'!G5:G200,"In Progress") -> 0
A64: =Stakeholders!B22 -> IT Infrastructure Lead | B64: =COUNTIF('Master Plan'!G5:G185,Stakeholders!A22) -> 3 | C64: =COUNTIF('Master Plan'!H5:H185,Stakeholders!A22) -> 4 | D64: =B64-COUNTIFS('Master Plan'!G5:G185,Stakeholders!A22,'Master Plan'!N5:N185,"Complete") -> 3 | E64: =COUNTIFS('Master Plan'!G5:G185,Stakeholders!A22,'Master Plan'!T5:T185,">0") -> 0 | F64: =COUNTIFS('RAID Log'!F5:F200,Stakeholders!A22,'RAID Log'!N5:N200,"Open")+COUNTIFS('RAID Log'!F5:F200,Stakeholders!A22,'RAID Log'!N5:N200,"In Progress") -> 1 | G64: =COUNTIFS('Action Log'!D5:D200,Stakeholders!A22,'Action Log'!G5:G200,"Open")+COUNTIFS('Action Log'!D5:D200,Stakeholders!A22,'Action Log'!G5:G200,"In Progress") -> 1
A65: =Stakeholders!B23 -> Cutover Manager | B65: =COUNTIF('Master Plan'!G5:G185,Stakeholders!A23) -> 4 | C65: =COUNTIF('Master Plan'!H5:H185,Stakeholders!A23) -> 1 | D65: =B65-COUNTIFS('Master Plan'!G5:G185,Stakeholders!A23,'Master Plan'!N5:N185,"Complete") -> 4 | E65: =COUNTIFS('Master Plan'!G5:G185,Stakeholders!A23,'Master Plan'!T5:T185,">0") -> 0 | F65: =COUNTIFS('RAID Log'!F5:F200,Stakeholders!A23,'RAID Log'!N5:N200,"Open")+COUNTIFS('RAID Log'!F5:F200,Stakeholders!A23,'RAID Log'!N5:N200,"In Progress") -> 0 | G65: =COUNTIFS('Action Log'!D5:D200,Stakeholders!A23,'Action Log'!G5:G200,"Open")+COUNTIFS('Action Log'!D5:D200,Stakeholders!A23,'Action Log'!G5:G200,"In Progress") -> 0
A66: =Stakeholders!B24 -> Hypercare Lead | B66: =COUNTIF('Master Plan'!G5:G185,Stakeholders!A24) -> 2 | C66: =COUNTIF('Master Plan'!H5:H185,Stakeholders!A24) -> 2 | D66: =B66-COUNTIFS('Master Plan'!G5:G185,Stakeholders!A24,'Master Plan'!N5:N185,"Complete") -> 2 | E66: =COUNTIFS('Master Plan'!G5:G185,Stakeholders!A24,'Master Plan'!T5:T185,">0") -> 0 | F66: =COUNTIFS('RAID Log'!F5:F200,Stakeholders!A24,'RAID Log'!N5:N200,"Open")+COUNTIFS('RAID Log'!F5:F200,Stakeholders!A24,'RAID Log'!N5:N200,"In Progress") -> 0 | G66: =COUNTIFS('Action Log'!D5:D200,Stakeholders!A24,'Action Log'!G5:G200,"Open")+COUNTIFS('Action Log'!D5:D200,Stakeholders!A24,'Action Log'!G5:G200,"In Progress") -> 0

Sheet Stakeholders
A1: Stakeholder Register
A2: Blue cells are inputs. Add or rename stakeholders here — dropdowns on every other sheet update automatically.
A4: Stakeholder ID | B4: Role (used in dropdowns) | C4: Name / Title | D4: Organisation | E4: Workstream | F4: Responsibilities | G4: Email | H4: Escalation Contact
A5: SH-01 | B5: Executive Sponsor | C5: VP Supply Chain Operations | D5: Leadership | E5: Sponsor | F5: Approves charter, budget, phase gates and go-live decision | G5: sponsor@company.com | H5: COO
A6: SH-02 | B6: Program Manager | C6: Senior Manager, PMO | D6: PMO | E6: PMO | F6: Owns the playbook, integrated plan, RAID log and gates
A7: SH-03 | B7: PMO Analyst | C7: Project Coordinator | D7: PMO | E7: PMO | F7: Maintains tracker, status reports, action log; runs AI Copilot outputs
A8: SH-04 | B8: Site / Facilities Lead | C8: Director, DC Engineering | D8: Facilities | E8: Site Readiness | F8: Building, utilities, racking, dock doors, permits
A9: SH-05 | B9: WMS Product Owner | C9: Senior Manager, WMS | D9: IT | E9: WMS / WCS | F9: WMS configuration, design decisions, backlog
A10: SH-06 | B10: WMS Tech Lead | C10: Staff Engineer, WMS | D10: IT | E10: WMS / WCS | F10: WMS build, interfaces, environments, code cutover
A11: SH-07 | B11: WCS / Automation Lead | C11: Manager, Automation Engineering | D11: Engineering | E11: Automation (MHE) | F11: Conveyor, sortation, robotics, WCS commissioning
A12: SH-08 | B12: Integration / ERP Lead | C12: Manager, Enterprise Integration | D12: IT | E12: Integration & Data | F12: ERP, OMS, TMS, EDI interfaces and middleware
A13: SH-09 | B13: Data Migration Lead | C13: Senior Data Engineer | D13: IT | E13: Integration & Data | F13: Item master, locations, inventory, customer and vendor data loads
A14: SH-10 | B14: QA / Test Manager | C14: Manager, Quality Engineering | D14: IT | E14: Testing | F14: Test strategy, SIT, UAT, performance test, defect triage
A15: SH-11 | B15: Operations Lead | C15: General Manager, DC | D15: Operations | E15: Operations & Staffing | F15: Process design, SOPs, hiring, shift model, go-live operations
A16: SH-12 | B16: Transportation Lead | C16: Manager, Transportation | D16: Transportation | E16: Transportation | F16: Carrier setup, yard, dock scheduling, TMS routing
A17: SH-13 | B17: Procurement / Vendor Lead | C17: Senior Buyer, Indirect Procurement | D17: Procurement | E17: Vendors | F17: MHE, WMS and construction vendor contracts, SOWs, milestones
... A24: SH-20 | B24: Hypercare Lead | C24: Support Manager, WMS | D24: IT | E24: Hypercare & Close | F24: Post go-live support, defect resolution, stabilisation metrics

Sheet Objectives
A1: Charter Objectives & Success Criteria (traceability anchor)
A2: Every deliverable and task in the Master Plan traces back to one of these objectives via the Objective ID column.
A4: Objective ID | B4: Objective | C4: Success Criteria / Measure | D4: Accountable (ID) | E4: Tasks Linked | F4: Tasks Complete | G4: % Complete | H4: Status
A5: OBJ-01 | B5: Open the greenfield DC on schedule with production go-live by the committed date | C5: Go-live date achieved; cutover completed within the planned window | D5: SH-01 | E5: =COUNTIF('Master Plan'!$D:$D,A5) -> 15 | F5: =COUNTIFS('Master Plan'!$D:$D,A5,'Master Plan'!$N:$N,"Complete") -> 4 | G5: =IF(E5=0,0,F5/E5) -> 0.26666667 | H5: =IF(E5=0,"No tasks",IF(G5=1,"Achieved",IF(COUNTIFS('Master Plan'!$D:$D,A5,'Master Plan'!$N:$N,"At Risk")+COUNTIFS('Master Plan'!$D:$D,A5,'Master Plan'!$N:$N,"Blocked")>0,"At Risk","On Track"))) -> On Track
A6: OBJ-02 | B6: Deliver a fully operational WMS / WCS stack with no Severity-1 defects at go-live | C6: Zero open Sev-1 defects at go / no-go; SIT and UAT exit criteria met | D6: SH-05 | E6: =COUNTIF('Master Plan'!$D:$D,A6) -> 20 | F6: 10 | G6: =IF(E6=0,0,F6/E6) -> 0.5 | H6: =IF(E6=0,"No tasks",IF(G6=1,"Achieved",IF(COUNTIFS('Master Plan'!$D:$D,A6,'Master Plan'!$N:$N,"At Risk")+COUNTIFS('Master Plan'!$D:$D,A6,'Master Plan'!$N:$N,"Blocked")>0,"At Risk","On Track"))) -> On Track
A7: OBJ-03 | B7: Commission automation (conveyor, sortation, robotics) at design throughput | C7: Throughput acceptance test passed at ≥ 95% of design rate | D7: SH-07 | E7: =COUNTIF('Master Plan'!$D:$D,A7) -> 9 | F7: =COUNTIFS('Master Plan'!$D:$D,A7,'Master Plan'!$N:$N,"Complete") -> 0 | G7: =IF(E7=0,0,F7/E7) -> 0 | H7: =IF(E7=0,"No tasks",IF(G7=1,"Achieved",IF(COUNTIFS('Master Plan'!$D:$D,A7,'Master Plan'!$N:$N,"At Risk")+COUNTIFS('Master Plan'!$D:$D,A7,'Master Plan'!$N:$N,"Blocked")>0,"At Risk","On Track"))) -> On Track
A8: OBJ-04 | B8: Stand up a trained, certified workforce and shift model before first receipt | C8: 100% of go-live associates trained and certified; supervisors signed off | D8: SH-11 | E8: =COUNTIF('Master Plan'!$D:$D,A8) -> 11 | F8: 5 | G8: =IF(E8=0,0,F8/E8) -> 0.45454545 | H8: =IF(E8=0,"No tasks",IF(G8=1,"Achieved",IF(COUNTIFS('Master Plan'!$D:$D,A8,'Master Plan'!$N:$N,"At Risk")+COUNTIFS('Master Plan'!$D:$D,A8,'Master Plan'!$N:$N,"Blocked")>0,"At Risk","On Track"))) -> On Track
A9: OBJ-05 | B9: Achieve site, safety and regulatory readiness | C9: Certificate of occupancy, fire, OSHA and equipment safety sign-offs complete | D9: SH-15 | E9: =COUNTIF('Master Plan'!$D:$D,A9) -> 7 | F9: =COUNTIFS('Master Plan'!$D:$D,A9,'Master Plan'!$N:$N,"Complete") -> 0 | G9: =IF(E9=0,0,F9/E9) -> 0 | H9: =IF(E9=0,"No tasks",IF(G9=1,"Achieved",IF(COUNTIFS('Master Plan'!$D:$D,A9,'Master Plan'!$N:$N,"At Risk")+COUNTIFS('Master Plan'!$D:$D,A9,'Master Plan'!$N:$N,"Blocked")>0,"At Risk","On Track"))) -> On Track
A10: OBJ-06 | B10: Connect inbound and outbound network flows (suppliers, carriers, ERP, TMS) | C10: EDI partners live; carriers onboarded; first inbound and outbound shipments executed | D10: SH-12 | E10: =COUNTIF('Master Plan'!$D:$D,A10) -> 11 | F10: =COUNTIFS('Master Plan'!$D:$D,A10,'Master Plan'!$N:$N,"Complete") -> 0 | G10: =IF(E10=0,0,F10/E10) -> 0 | H10: =IF(E10=0,"No tasks",IF(G10=1,"Achieved",IF(COUNTIFS('Master Plan'!$D:$D,A10,'Master Plan'!$N:$N,"At Risk")+COUNTIFS('Master Plan'!$D:$D,A10,'Master Plan'!$N:$N,"Blocked")>0,"At Risk","On Track"))) -> On Track
A11: OBJ-07 | B11: Deliver within approved capex and opex budget | C11: Actual spend within ±5% of approved budget at close | D11: SH-16 | E11: =COUNTIF('Master Plan'!$D:$D,A11) -> 4 | F11: 3 | G11: =IF(E11=0,0,F11/E11) -> 0.75 | H11: =IF(E11=0,"No tasks",IF(G11=1,"Achieved",IF(COUNTIFS('Master Plan'!$D:$D,A11,'Master Plan'!$N:$N,"At Risk")+COUNTIFS('Master Plan'!$D:$D,A11,'Master Plan'!$N:$N,"Blocked")>0,"At Risk","On Track"))) -> On Track
A12: OBJ-08 | B12: Stabilise operations and hand over to run organisation | C12: Hypercare exit criteria met; lessons learned published; templates updated | D12: SH-20 | E12: =COUNTIF('Master Plan'!$D:$D,A12) -> 4 | F12: 2 | G12: =IF(E12=0,0,F12/E12) -> 0.5 | H12: =IF(E12=0,"No tasks",IF(G12=1,"Achieved",IF(COUNTIFS('Master Plan'!$D:$D,A12,'Master Plan'!$N:$N,"At Risk")+COUNTIFS('Master Plan'!$D:$D,A12,'Master Plan'!$N:$N,"Blocked")>0,"At Risk","On Track"))) -> On Track

Sheet Master Plan
A1: Master Plan & Traceability Matrix — Greenfield Supply Chain Go-Live
A2: One row per task. Blue = input. Grey = formula (do not edit). Owners are Stakeholder IDs; R/A/C/I trace every stakeholder to every task. Status drives Dashboard, Objectives and Gates.
A4: Task ID | B4: Phase | C4: Workstream | D4: Objective ID | E4: Deliverable | F4: Task / Activity | G4: Responsible (ID) | H4: Accountable (ID) | I4: Consulted (ID) | J4: Informed (ID) | K4: Start | L4: Due | M4: Duration (days) | N4: Status | O4: % Complete | P4: Predecessors | Q4: AI Copilot Moment | R4: Gate | S4: Evidence / Link | T4: Days Overdue | U4: Health | V4: Last Updated | W4: Notes
A5: T-001 | B5: 1. Initiation | C5: PMO | D5: OBJ-01 | E5: Project Charter | F5: Draft charter from business case using AI Copilot (scope, objectives, success metrics, constraints) | G5: SH-02 | H5: SH-01 | I5: SH-16 | J5: SH-11 | K5: 46300 | L5: 46306 | M5: =IF(OR(K5="",L5=""),"",L5-K5+1) -> 7 | N5: Complete | O5: 1 | Q5: Intake | R5: G1 | T5: =IF(OR(N5="Complete",N5="Deferred",L5=""),0,MAX(0,TODAY()-L5)) -> 0 | U5: =IF(N5="Complete","Done",IF(OR(N5="Blocked",T5>5),"Red",IF(OR(N5="At Risk",T5>0,AND(N5="Not Started",K5<TODAY())),"Amber","Green"))) -> Done | V5: 46321
A6: T-002 | B6: 1. Initiation | C6: PMO | D6: OBJ-01 | E6: Project Charter | F6: Review and approve charter | G6: SH-01 | H6: SH-01 | I6: SH-02 | J6: SH-03 | K6: 46307 | L6: 46313 | M6: =IF(OR(K6="",L6=""),"",L6-K6+1) -> 7 | N6: Complete | O6: 1 | P6: T-001 | Q6: Intake | R6: G1 | T6: =IF(OR(N6="Complete",N6="Deferred",L6=""),0,MAX(0,TODAY()-L6)) -> 0 | U6: =IF(N6="Complete","Done",IF(OR(N6="Blocked",T6>5),"Red",IF(OR(N6="At Risk",T6>0,AND(N6="Not Started",K6<TODAY())),"Amber","Green"))) -> Done | V6: 46321
A7: T-003 | B7: 1. Initiation | C7: PMO | D7: OBJ-01 | E7: Stakeholder Register | F7: Identify stakeholders, confirm roles and escalation paths | G7: SH-02 | H7: SH-01 | I7: SH-11 | J7: SH-03 | K7: 46300 | L7: 46306 | M7: =IF(OR(K7="",L7=""),"",L7-K7+1) -> 7 | N7: Complete | O7: 1 | Q7: Intake | R7: G1 | T7: =IF(OR(N7="Complete",N7="Deferred",L7=""),0,MAX(0,TODAY()-L7)) -> 0 | U7: =IF(N7="Complete","Done",IF(OR(N7="Blocked",T7>5),"Red",IF(OR(N7="At Risk",T7>0,AND(N7="Not Started",K7<TODAY())),"Amber","Green"))) -> Done | V7: 46321
A8: T-004 | B8: 1. Initiation | C8: Finance | D8: OBJ-07 | E8: Budget Baseline | F8: Approve capex / opex baseline and funding release | G8: SH-16 | H8: SH-01 | I8: SH-02 | J8: SH-13 | K8: 46307 | L8: 46320 | M8: =IF(OR(K8="",L8=""),"",L8-K8+1) -> 14 | N8: Complete | O8: 1 | P8: T-002 | Q8: Intake | R8: G1 | T8: =IF(OR(N8="Complete",N8="Deferred",L8=""),0,MAX(0,TODAY()-L8)) -> 0 | U8: =IF(N8="Complete","Done",IF(OR(N8="Blocked",T8>5),"Red",IF(OR(N8="At Risk",T8>0,AND(N8="Not Started",K8<TODAY())),"Amber","Green"))) -> Done | V8: 46321
A9: T-005 | B9: 1. Initiation | C9: PMO | D9: OBJ-01 | E9: Governance Model | F9: Set up steering committee cadence, RAID log and Completeness Gate checklists | G9: SH-02 | H9: SH-01 | I9: SH-03 | J9: SH-11 | K9: 46307 | L9: 46313 | M9: =IF(OR(K9="",L9=""),"",L9-K9+1) -> 7 | N9: Complete | O9: 1 | P9: T-002 | Q9: Plan | R9: G1 | T9: =IF(OR(N9="Complete",N9="Deferred",L9=""),0,MAX(0,TODAY()-L9)) -> 0 | U9: =IF(N9="Complete","Done",IF(OR(N9="Blocked",T9>5),"Red",IF(OR(N9="At Risk",T9>0,AND(N9="Not Started",K9<TODAY())),"Amber","Green"))) -> Done | V9: 46321
A10: T-006 | B10: 1. Initiation | C10: Vendors | D10: OBJ-03 | E10: Vendor Shortlist | F10: Confirm MHE, WMS and construction vendors and SOW status | G10: SH-13 | H10: SH-02 | I10: SH-07 | J10: SH-16 | K10: 46307 | L10: 46320 | M10: =IF(OR(K10="",L10=""),"",L10-K10+1) -> 14 | N10: In Progress | O10: 0.4 | Q10: Intake | R10: G1 | T10: =IF(OR(N10="Complete",N10="Deferred",L10=""),0,MAX(0,TODAY()-L10)) -> 0 | U10: =IF(N10="Complete","Done",IF(OR(N10="Blocked",T10>5),"Red",IF(OR(N10="At Risk",T10>0,AND(N10="Not Started",K10<TODAY())),"Amber","Green"))) -> Green | V10: 46321
A11: T-007 | B11: 1. Initiation | C11: PMO | D11: OBJ-01 | E11: Gate 1 Review | F11: Completeness Gate 1: charter, budget, stakeholders, governance approved | G11: SH-02 | H11: SH-01 | I11: SH-03 | J11: SH-11 | K11: 46321 | L11: 46327 | M11: =IF(OR(K11="",L11=""),"",L11-K11+1) -> 7 | N11: In Progress | O11: 0.4 | P11: T-002,T-004,T-005 | Q11: Communicate | R11: G1 | T11: =IF(OR(N11="Complete",N11="Deferred",L11=""),0,MAX(0,TODAY()-L11)) -> 0 | U11: =IF(N11="Complete","Done",IF(OR(N11="Blocked",T11>5),"Red",IF(OR(N11="At Risk",T11>0,AND(N11="Not Started",K11<TODAY())),"Amber","Green"))) -> Green | V11: 46321
A12: T-008 | B12: 2. Planning & Design | C12: PMO | D12: OBJ-01 | E12: Integrated Master Plan | F12: Generate WBS from greenfield template; confirm dependencies and critical path | G12: SH-02 | H12: SH-01 | I12: SH-05 | J12: SH-11 | K12: 46321 | L12: 46334 | M12: =IF(OR(K12="",L12=""),"",L12-K12+1) -> 14 | N12: In Progress | O12: 0.4 | P12: T-007 | Q12: Plan | R12: G2 | T12: =IF(OR(N12="Complete",N12="Deferred",L12=""),0,MAX(0,TODAY()-L12)) -> 0 | U12: =IF(N12="Complete","Done",IF(OR(N12="Blocked",T12>5),"Red",IF(OR(N12="At Risk",T12>0,AND(N12="Not Started",K12<TODAY())),"Amber","Green"))) -> Green | V12: 46321
A13: T-009 | B13: 2. Planning & Design | C13: PMO | D13: OBJ-01 | E13: RAID Baseline | F13: Create RAID baseline with owners and due dates | G13: SH-02 | H13: SH-02 | I13: SH-05 | J13: SH-01 | K13: 46321 | L13: 46327 | M13: =IF(OR(K13="",L13=""),"",L13-K13+1) -> 7 | N13: Not Started | O13: 0 | P13: T-007 | Q13: Plan | R13: G2 | T13: =IF(OR(N13="Complete",N13="Deferred",L13=""),0,MAX(0,TODAY()-L13)) -> 0 | U13: =IF(N13="Complete","Done",IF(OR(N13="Blocked",T13>5),"Red",IF(OR(N13="At Risk",T13>0,AND(N13="Not Started",K13<TODAY())),"Amber","Green"))) -> Green | V13: 46321
A14: T-010 | B14: 2. Planning & Design | C14: Site Readiness | D14: OBJ-05 | E14: Facility Design | F14: Finalise building layout, racking, dock doors and utilities design | G14: SH-04 | H14: SH-04 | I14: SH-07 | J14: SH-11 | K14: 46321 | L14: 46348 | M14: =IF(OR(K14="",L14=""),"",L14-K14+1) -> 28 | N14: Not Started | O14: 0 | P14: T-008 | Q14: Plan | R14: G2 | T14: =IF(OR(N14="Complete",N14="Deferred",L14=""),0,MAX(0,TODAY()-L14)) -> 0 | U14: =IF(N14="Complete","Done",IF(OR(N14="Blocked",T14>5),"Red",IF(OR(N14="At Risk",T14>0,AND(N14="Not Started",K14<TODAY())),"Amber","Green"))) -> Green
A15: T-011 | B15: 2. Planning & Design | C15: Site Readiness | D15: OBJ-05 | E15: Permits | F15: Submit building, fire and occupancy permit applications | G15: SH-04 | H15: SH-04 | I15: SH-15 | J15: SH-02 | K15: 46335 | L15: 46355 | M15: =IF(OR(K15="",L15=""),"",L15-K15+1) -> 21 | N15: Not Started | O15: 0 | P15: T-010 | Q15: Monitor | R15: G2 | T15: =IF(OR(N15="Complete",N15="Deferred",L15=""),0,MAX(0,TODAY()-L15)) -> 0 | U15: =IF(N15="Complete","Done",IF(OR(N15="Blocked",T15>5),"Red",IF(OR(N15="At Risk",T15>0,AND(N15="Not Started",K15<TODAY())),"Amber","Green"))) -> Green
A16: T-012 | B16: 2. Planning & Design | C16: Operations & Staffing | D16: OBJ-04 | E16: Process Design | F16: Design inbound, putaway, pick, pack, ship and returns processes (to-be) | G16: SH-11 | H16: SH-11 | I16: SH-05 | J16: SH-17 | K16: 46328 | L16: 46355 | M16: =IF(OR(K16="",L16=""),"",L16-K16+1) -> 28 | N16: Not Started | O16: 0 | P16: T-008 | Q16: Plan | R16: G2 | T16: =IF(OR(N16="Complete",N16="Deferred",L16=""),0,MAX(0,TODAY()-L16)) -> 0 | U16: =IF(N16="Complete","Done",IF(OR(N16="Blocked",T16>5),"Red",IF(OR(N16="At Risk",T16>0,AND(N16="Not Started",K16<TODAY())),"Amber","Green"))) -> Green
A17: T-013 | B17: 2. Planning & Design | C17: WMS / WCS | D17: OBJ-02 | E17: WMS Functional Design | F17: Fit-gap workshops and functional design document sign-off | G17: SH-05 | H17: SH-05 | I17: SH-11 | J17: SH-06 | K17: 46335 | L17: 46362 | M17: =IF(OR(K17="",L17=""),"",L17-K17+1) -> 28 | N17: Not Started | O17: 0 | P17: T-012 | Q17: Plan | R17: G2 | T17: =IF(OR(N17="Complete",N17="Deferred",L17=""),0,MAX(0,TODAY()-L17)) -> 0 | U17: =IF(N17="Complete","Done",IF(OR(N17="Blocked",T17>5),"Red",IF(OR(N17="At Risk",T17>0,AND(N17="Not Started",K17<TODAY())),"Amber","Green"))) -> Green
A18: T-014 | B18: 2. Planning & Design | C18: WMS / WCS | D18: OBJ-02 | E18: WMS Technical Design | F18: Technical design: environments, interfaces, data model, security | G18: SH-06 | H18: SH-05 | I18: SH-08 | J18: SH-18 | K18: 46342 | L18: 46362 | M18: =IF(OR(K18="",L18=""),"",L18-K18+1) -> 21 | N18: Not Started | O18: 0 | P18: T-013 | Q18: Plan | R18: G2 | T18: =IF(OR(N18="Complete",N18="Deferred",L18=""),0,MAX(0,TODAY()-L18)) -> 0 | U18: =IF(N18="Complete","Done",IF(OR(N18="Blocked",T18>5),"Red",IF(OR(N18="At Risk",T18>0,AND(N18="Not Started",K18<TODAY())),"Amber","Green"))) -> Green
A19: T-015 | B19: 2. Planning & Design | C19: Automation (MHE) | D19: OBJ-03 | E19: Automation Design | F19: Approve MHE layout, throughput model and WCS control philosophy | G19: SH-07 | H19: SH-07 | I19: SH-14 | J19: SH-05 | K19: 46328 | L19: 46362 | M19: =IF(OR(K19="",L19=""),"",L19-K19+1) -> 35 | N19: Not Started | O19: 0 | P19: T-010 | Q19: Plan | R19: G2 | T19: =IF(OR(N19="Complete",N19="Deferred",L19=""),0,MAX(0,TODAY()-L19)) -> 0 | U19: =IF(N19="Complete","Done",IF(OR(N19="Blocked",T19>5),"Red",IF(OR(N19="At Risk",T19>0,AND(N19="Not Started",K19<TODAY())),"Amber","Green"))) -> Green
A20: T-016 | B20: 2. Planning & Design | C20: Integration & Data | D20: OBJ-06 | E20: Interface Catalogue | F20: Define all ERP / OMS / TMS / WCS / EDI interfaces with owners | G20: SH-08 | H20: SH-08 | I20: SH-06 | J20: SH-12 | K20: 46342 | L20: 46362 | M20: =IF(OR(K20="",L20=""),"",L20-K20+1) -> 21 | N20: Not Started | O20: 0 | P20: T-014 | Q20: Plan | R20: G2 | T20: =IF(OR(N20="Complete",N20="Deferred",L20=""),0,MAX(0,TODAY()-L20)) -> 0 | U20: =IF(N20="Complete","Done",IF(OR(N20="Blocked",T20>5),"Red",IF(OR(N20="At Risk",T20>0,AND(N20="Not Started",K20<TODAY())),"Amber","Green"))) -> Green
A21: T-017 | B21: 2. Planning & Design | C21: Integration & Data | D21: OBJ-02 | E21: Data Migration Strategy | F21: Define data objects, sources, cleansing rules and load sequence | G21: SH-09 | H21: SH-08 | I21: SH-05 | J21: SH-11 | K21: 46349 | L21: 46362 | M21: =IF(OR(K21="",L21=""),"",L21-K21+1) -> 14 | N21: Not Started | O21: 0 | P21: T-016 | Q21: Plan | R21: G2 | T21: =IF(OR(N21="Complete",N21="Deferred",L21=""),0,MAX(0,TODAY()-L21)) -> 0 | U21: =IF(N21="Complete","Done",IF(OR(N21="Blocked",T21>5),"Red",IF(OR(N21="At Risk",T21>0,AND(N21="Not Started",K21<TODAY())),"Amber","Green"))) -> Green
A22: T-018 | B22: 2. Planning & Design | C22: Testing | D22: OBJ-02 | E22: Test Strategy | F22: Approve test strategy: unit, SIT, UAT, performance, throughput acceptance | G22: SH-10 | H22: SH-10 | I22: SH-05 | J22: SH-07 | K22: 46356 | L22: 46369 | M22: =IF(OR(K22="",L22=""),"",L22-K22+1) -> 14 | N22: Not Started | O22: 0 | P22: T-013 | Q22: Plan | R22: G2 | T22: =IF(OR(N22="Complete",N22="Deferred",L22=""),0,MAX(0,TODAY()-L22)) -> 0 | U22: =IF(N22="Complete","Done",IF(OR(N22="Blocked",T22>5),"Red",IF(OR(N22="At Risk",T22>0,AND(N22="Not Started",K22<TODAY())),"Amber","Green"))) -> Green
A23: T-019 | B23: 2. Planning & Design | C23: Infrastructure | D23: OBJ-02 | E23: Infrastructure Design | F23: Design network, Wi-Fi survey, RF devices, printers, server / cloud | G23: SH-18 | H23: SH-18 | I23: SH-06 | J23: SH-04 | K23: 46342 | L23: 46362 | M23: =IF(OR(K23="",L23=""),"",L23-K23+1) -> 21 | N23: Not Started | O23: 0 | P23: T-010 | Q23: Plan | R23: G2 | T23: =IF(OR(N23="Complete",N23="Deferred",L23=""),0,MAX(0,TODAY()-L23)) -> 0 | U23: =IF(N23="Complete","Done",IF(OR(N23="Blocked",T23>5),"Red",IF(OR(N23="At Risk",T23>0,AND(N23="Not Started",K23<TODAY())),"Amber","Green"))) -> Green
A24: T-020 | B24: 2. Planning & Design | C24: Transportation | D24: OBJ-06 | E24: Transportation Design | F24: Design carrier network, yard and dock scheduling, TMS routing | G24: SH-12 | H24: SH-12 | I24: SH-11 | J24: SH-08 | K24: 46349 | L24: 46369 | M24: =IF(OR(K24="",L24=""),"",L24-K24+1) -> 21 | N24: Not Started | O24: 0 | P24: T-012 | Q24: Plan | R24: G2 | T24: =IF(OR(N24="Complete",N24="Deferred",L24=""),0,MAX(0,TODAY()-L24)) -> 0 | U24: =IF(N24="Complete","Done",IF(OR(N24="Blocked",T24>5),"Red",IF(OR(N24="At Risk",T24>0,AND(N24="Not Started",K24<TODAY())),"Amber","Green"))) -> Green
A25: T-021 | B25: 2. Planning & Design | C25: Change & Training | D25: OBJ-04 | E25: Change Plan | F25: Change impact assessment, communication and training plan | G25: SH-17 | H25: SH-17 | I25: SH-11 | J25: SH-02 | K25: 46356 | L25: 46369 | M25: =IF(OR(K25="",L25=""),"",L25-K25+1) -> 14 | N25: Not Started | O25: 0 | P25: T-012 | Q25: Plan | R25: G2 | T25: =IF(OR(N25="Complete",N25="Deferred",L25=""),0,MAX(0,TODAY()-L25)) -> 0 | U25: =IF(N25="Complete","Done",IF(OR(N25="Blocked",T25>5),"Red",IF(OR(N25="At Risk",T25>0,AND(N25="Not Started",K25<TODAY())),"Amber","Green"))) -> Green
... A42: T-038 | B42: 3. Build & Configure | C42: Finance | D42: OBJ-07 | E42: Capex Tracking | F42: Monthly capex vs. budget review with variance explanations | G42: SH-16 | H42: SH-16 | I42: SH-02 | J42: SH-01 | K42: 46384 | L42: 46481 | M42: =IF(OR(K42="",L42=""),"",L42-K42+1) -> 98 | N42: Not Started | O42: 0 | P42: T-004 | Q42: Communicate | R42: G3 | T42: =IF(OR(N42="Complete",N42="Deferred",L42=""),0,MAX(0,TODAY()-L42)) -> 0 | U42: =IF(N42="Complete","Done",IF(OR(N42="Blocked",T42>5),"Red",IF(OR(N42="At Risk",T42>0,AND(N42="Not Started",K42<TODAY())),"Amber","Green"))) -> Green
A43: T-039 | B43: 3. Build & Configure | C43: PMO | D43: OBJ-01 | E43: Weekly Status Report | F43: AI-drafted weekly status and exception review (recurring through go-live) | G43: SH-03 | H43: SH-02 | I43: SH-05 | J43: SH-01 | K43: 46384 | L43: 46481 | M43: =IF(OR(K43="",L43=""),"",L43-K43+1) -> 98 | N43: Not Started | O43: 0 | P43: T-007 | Q43: Communicate | T43: =IF(OR(N43="Complete",N43="Deferred",L43=""),0,MAX(0,TODAY()-L43)) -> 0 | U43: =IF(N43="Complete","Done",IF(OR(N43="Blocked",T43>5),"Red",IF(OR(N43="At Risk",T43>0,AND(N43="Not Started",K43<TODAY())),"Amber","Green"))) -> Green
A44: T-040 | B44: 3. Build & Configure | C44: PMO | D44: OBJ-01 | E44: Gate 3 Review | F44: Completeness Gate 3: build complete, construction and equipment on schedule | G44: SH-02 | H44: SH-01 | I44: SH-06 | J44: SH-07 | K44: 46475 | L44: 46481 | M44: =IF(OR(K44="",L44=""),"",L44-K44+1) -> 7 | N44: Not Started | O44: 0 | P44: T-024,T-025,T-027,T-033 | Q44: Communicate | R44: G3 | T44: =IF(OR(N44="Complete",N44="Deferred",L44=""),0,MAX(0,TODAY()-L44)) -> 0 | U44: =IF(N44="Complete","Done",IF(OR(N44="Blocked",T44>5),"Red",IF(OR(N44="At Risk",T44>0,AND(N44="Not Started",K44<TODAY())),"Amber","Green"))) -> Green
A45: T-041 | B45: 4. Site Readiness | C45: Site Readiness | D45: OBJ-05 | E45: Racking Install | F45: Install racking, mezzanine and dock equipment | G45: SH-04 | H45: SH-04 | I45: SH-15 | J45: SH-11 | K45: 46468 | L45: 46502 | M45: =IF(OR(K45="",L45=""),"",L45-K45+1) -> 35 | N45: Not Started | O45: 0 | P45: T-033 | Q45: Monitor | R45: G4 | T45: =IF(OR(N45="Complete",N45="Deferred",L45=""),0,MAX(0,TODAY()-L45)) -> 0 | U45: =IF(N45="Complete","Done",IF(OR(N45="Blocked",T45>5),"Red",IF(OR(N45="At Risk",T45>0,AND(N45="Not Started",K45<TODAY())),"Amber","Green"))) -> Green
A46: T-042 | B46: 4. Site Readiness | C46: Automation (MHE) | D46: OBJ-03 | E46: MHE Installation | F46: Mechanical and electrical installation of automation | G46: SH-14 | H46: SH-07 | I46: SH-04 | J46: SH-15 | K46: 46482 | L46: 46523 | M46: =IF(OR(K46="",L46=""),"",L46-K46+1) -> 42 | N46: Not Started | O46: 0 | P46: T-031,T-033 | Q46: Monitor | R46: G4 | T46: =IF(OR(N46="Complete",N46="Deferred",L46=""),0,MAX(0,TODAY()-L46)) -> 0 | U46: =IF(N46="Complete","Done",IF(OR(N46="Blocked",T46>5),"Red",IF(OR(N46="At Risk",T46>0,AND(N46="Not Started",K46<TODAY())),"Amber","Green"))) -> Green
A47: T-043 | B47: 4. Site Readiness | C47: Automation (MHE) | D47: OBJ-03 | E47: MHE Commissioning | F47: Dry commissioning and WCS control testing | G47: SH-14 | H47: SH-07 | I47: SH-06 | J47: SH-10 | K47: 46517 | L47: 46537 | M47: =IF(OR(K47="",L47=""),"",L47-K47+1) -> 21 | N47: Not Started | O47: 0 | P47: T-042,T-032 | Q47: Monitor | R47: G4 | T47: =IF(OR(N47="Complete",N47="Deferred",L47=""),0,MAX(0,TODAY()-L47)) -> 0 | U47: =IF(N47="Complete","Done",IF(OR(N47="Blocked",T47>5),"Red",IF(OR(N47="At Risk",T47>0,AND(N47="Not Started",K47<TODAY())),"Amber","Green"))) -> Green
A48: T-044 | B48: 4. Site Readiness | C48: Safety & Compliance | D48: OBJ-05 | E48: Safety Inspections | F48: Fire marshal, OSHA and equipment safety inspections | G48: SH-15 | H48: SH-15 | I48: SH-04 | J48: SH-02 | K48: 46510 | L48: 46530 | M48: =IF(OR(K48="",L48=""),"",L48-K48+1) -> 21 | N48: Not Started | O48: 0 | P48: T-041,T-042 | Q48: Monitor | R48: G4 | T48: =IF(OR(N48="Complete",N48="Deferred",L48=""),0,MAX(0,TODAY()-L48)) -> 0 | U48: =IF(N48="Complete","Done",IF(OR(N48="Blocked",T48>5),"Red",IF(OR(N48="At Risk",T48>0,AND(N48="Not Started",K48<TODAY())),"Amber","Green"))) -> Green
A49: T-045 | B49: 4. Site Readiness | C49: Safety & Compliance | D49: OBJ-05 | E49: Certificate of Occupancy | F49: Obtain certificate of occupancy | G49: SH-04 | H49: SH-15 | I49: SH-02 | J49: SH-01 | K49: 46524 | L49: 46537 | M49: =IF(OR(K49="",L49=""),"",L49-K49+1) -> 14 | N49: Not Started | O49: 0 | P49: T-044 | Q49: Monitor | R49: G4 | T49: =IF(OR(N49="Complete",N49="Deferred",L49=""),0,MAX(0,TODAY()-L49)) -> 0 | U49: =IF(N49="Complete","Done",IF(OR(N49="Blocked",T49>5),"Red",IF(OR(N49="At Risk",T49>0,AND(N49="Not Started",K49<TODAY())),"Amber","Green"))) -> Green
A50: T-046 | B50: 4. Site Readiness | C50: Operations & Staffing | D50: OBJ-04 | E50: Supervisor Hiring | F50: Hire and onboard supervisors and leads | G50: SH-11 | H50: SH-11 | I50: SH-17 | J50: SH-02 | K50: 46468 | L50: 46509 | M50: =IF(OR(K50="",L50=""),"",L50-K50+1) -> 42 | N50: Not Started | O50: 0 | P50: T-036 | Q50: Monitor | R50: G4 | T50: =IF(OR(N50="Complete",N50="Deferred",L50=""),0,MAX(0,TODAY()-L50)) -> 0 | U50: =IF(N50="Complete","Done",IF(OR(N50="Blocked",T50>5),"Red",IF(OR(N50="At Risk",T50>0,AND(N50="Not Started",K50<TODAY())),"Amber","Green"))) -> Green
A51: T-047 | B51: 4. Site Readiness | C51: Infrastructure | D51: OBJ-02 | E51: Site IT Go-Live | F51: Site network, RF and printers live and tested | G51: SH-18 | H51: SH-18 | I51: SH-06 | J51: SH-11 | K51: 46496 | L51: 46509 | M51: =IF(OR(K51="",L51=""),"",L51-K51+1) -> 14 | N51: Not Started | O51: 0 | P51: T-034 | Q51: Monitor | R51: G4 | T51: =IF(OR(N51="Complete",N51="Deferred",L51=""),0,MAX(0,TODAY()-L51)) -> 0 | U51: =IF(N51="Complete","Done",IF(OR(N51="Blocked",T51>5),"Red",IF(OR(N51="At Risk",T51>0,AND(N51="Not Started",K51<TODAY())),"Amber","Green"))) -> Green
A52: T-048 | B52: 4. Site Readiness | C52: Transportation | D52: OBJ-06 | E52: Yard & Dock Setup | F52: Yard management, dock scheduling and gate procedures ready | G52: SH-12 | H52: SH-12 | I52: SH-11 | J52: SH-04 | K52: 46510 | L52: 46530 | M52: =IF(OR(K52="",L52=""),"",L52-K52+1) -> 21 | N52: Not Started | O52: 0 | P52: T-037,T-041 | Q52: Monitor | R52: G4 | T52: =IF(OR(N52="Complete",N52="Deferred",L52=""),0,MAX(0,TODAY()-L52)) -> 0 | U52: =IF(N52="Complete","Done",IF(OR(N52="Blocked",T52>5),"Red",IF(OR(N52="At Risk",T52>0,AND(N52="Not Started",K52<TODAY())),"Amber","Green"))) -> Green
A53: T-049 | B53: 4. Site Readiness | C53: PMO | D53: OBJ-05 | E53: Gate 4 Review | F53: Completeness Gate 4: site, safety, equipment and infrastructure ready | G53: SH-02 | H53: SH-01 | I53: SH-04 | J53: SH-15 | K53: 46538 | L53: 46544 | M53: =IF(OR(K53="",L53=""),"",L53-K53+1) -> 7 | N53: Not Started | O53: 0 | P53: T-043,T-045,T-047 | Q53: Communicate | R53: G4 | T53: =IF(OR(N53="Complete",N53="Deferred",L53=""),0,MAX(0,TODAY()-L53)) -> 0 | U53: =IF(N53="Complete","Done",IF(OR(N53="Blocked",T53>5),"Red",IF(OR(N53="At Risk",T53>0,AND(N53="Not Started",K53<TODAY())),"Amber","Green"))) -> Green
A54: T-050 | B54: 5. Integration & Testing | C54: Testing | D54: OBJ-02 | E54: System Integration Test | F54: SIT cycles 1-2 across WMS, ERP, OMS, TMS and WCS emulation | G54: SH-10 | H54: SH-10 | I54: SH-06 | J54: SH-05 | K54: 46482 | L54: 46523 | M54: =IF(OR(K54="",L54=""),"",L54-K54+1) -> 42 | N54: Not Started | O54: 0 | P54: T-027,T-030 | Q54: Monitor | R54: G5 | T54: =IF(OR(N54="Complete",N54="Deferred",L54=""),0,MAX(0,TODAY()-L54)) -> 0 | U54: =IF(N54="Complete","Done",IF(OR(N54="Blocked",T54>5),"Red",IF(OR(N54="At Risk",T54>0,AND(N54="Not Started",K54<TODAY())),"Amber","Green"))) -> Green
A55: T-051 | B55: 5. Integration & Testing | C55: Testing | D55: OBJ-02 | E55: Defect Management | F55: Daily defect triage; Sev-1 / Sev-2 burn-down tracked | G55: SH-10 | H55: SH-05 | I55: SH-06 | J55: SH-02 | K55: 46482 | L55: 46579 | M55: =IF(OR(K55="",L55=""),"",L55-K55+1) -> 98 | N55: Not Started | O55: 0 | P55: T-050 | Q55: Monitor | T55: =IF(OR(N55="Complete",N55="Deferred",L55=""),0,MAX(0,TODAY()-L55)) -> 0 | U55: =IF(N55="Complete","Done",IF(OR(N55="Blocked",T55>5),"Red",IF(OR(N55="At Risk",T55>0,AND(N55="Not Started",K55<TODAY())),"Amber","Green"))) -> Green
A56: T-052 | B56: 5. Integration & Testing | C56: Integration & Data | D56: OBJ-02 | E56: Mock Data Load 2 | F56: Full-volume mock migration with reconciliation report | G56: SH-09 | H56: SH-08 | I56: SH-06 | J56: SH-10 | K56: 46524 | L56: 46537 | M56: =IF(OR(K56="",L56=""),"",L56-K56+1) -> 14 | N56: Not Started | O56: 0 | P56: T-030 | Q56: Monitor | R56: G5 | T56: =IF(OR(N56="Complete",N56="Deferred",L56=""),0,MAX(0,TODAY()-L56)) -> 0 | U56: =IF(N56="Complete","Done",IF(OR(N56="Blocked",T56>5),"Red",IF(OR(N56="At Risk",T56>0,AND(N56="Not Started",K56<TODAY())),"Amber","Green"))) -> Green
A57: T-053 | B57: 5. Integration & Testing | C57: Testing | D57: OBJ-02 | E57: Performance Test | F57: Peak-volume performance and interface load test | G57: SH-10 | H57: SH-06 | I57: SH-08 | J57: SH-18 | K57: 46531 | L57: 46544 | M57: =IF(OR(K57="",L57=""),"",L57-K57+1) -> 14 | N57: Not Started | O57: 0 | P57: T-050,T-052 | Q57: Monitor | R57: G5 | T57: =IF(OR(N57="Complete",N57="Deferred",L57=""),0,MAX(0,TODAY()-L57)) -> 0 | U57: =IF(N57="Complete","Done",IF(OR(N57="Blocked",T57>5),"Red",IF(OR(N57="At Risk",T57>0,AND(N57="Not Started",K57<TODAY())),"Amber","Green"))) -> Green
A58: T-054 | B58: 5. Integration & Testing | C58: Automation (MHE) | D58: OBJ-03 | E58: Throughput Acceptance Test | F58: Integrated WMS / WCS / MHE throughput test at design rate | G58: SH-07 | H58: SH-07 | I58: SH-14 | J58: SH-11 | K58: 46538 | L58: 46558 | M58: =IF(OR(K58="",L58=""),"",L58-K58+1) -> 21 | N58: Not Started | O58: 0 | P58: T-043,T-050 | Q58: Monitor | R58: G5 | T58: =IF(OR(N58="Complete",N58="Deferred",L58=""),0,MAX(0,TODAY()-L58)) -> 0 | U58: =IF(N58="Complete","Done",IF(OR(N58="Blocked",T58>5),"Red",IF(OR(N58="At Risk",T58>0,AND(N58="Not Started",K58<TODAY())),"Amber","Green"))) -> Green
A59: T-055 | B59: 5. Integration & Testing | C59: Testing | D59: OBJ-02 | E59: User Acceptance Test | F59: UAT with operations super-users; exit criteria signed | G59: SH-11 | H59: SH-05 | I59: SH-10 | J59: SH-17 | K59: 46545 | L59: 46572 | M59: =IF(OR(K59="",L59=""),"",L59-K59+1) -> 28 | N59: Not Started | O59: 0 | P59: T-050,T-035 | Q59: Monitor | R59: G5 | T59: =IF(OR(N59="Complete",N59="Deferred",L59=""),0,MAX(0,TODAY()-L59)) -> 0 | U59: =IF(N59="Complete","Done",IF(OR(N59="Blocked",T59>5),"Red",IF(OR(N59="At Risk",T59>0,AND(N59="Not Started",K59<TODAY())),"Amber","Green"))) -> Green
A60: T-056 | B60: 5. Integration & Testing | C60: Transportation | D60: OBJ-06 | E60: Carrier Connectivity Test | F60: End-to-end label, manifest and EDI 214/210 test with carriers | G60: SH-12 | H60: SH-12 | I60: SH-08 | J60: SH-10 | K60: 46552 | L60: 46565 | M60: =IF(OR(K60="",L60=""),"",L60-K60+1) -> 14 | N60: Not Started | O60: 0 | P60: T-037,T-028 | Q60: Monitor | R60: G5 | T60: =IF(OR(N60="Complete",N60="Deferred",L60=""),0,MAX(0,TODAY()-L60)) -> 0 | U60: =IF(N60="Complete","Done",IF(OR(N60="Blocked",T60>5),"Red",IF(OR(N60="At Risk",T60>0,AND(N60="Not Started",K60<TODAY())),"Amber","Green"))) -> Green
A61: T-057 | B61: 5. Integration & Testing | C61: Integration & Data | D61: OBJ-06 | E61: Supplier EDI Test | F61: Test ASN / PO / invoice with priority suppliers | G61: SH-08 | H61: SH-08 | I61: SH-13 | J61: SH-11 | K61: 46552 | L61: 46565 | M61: =IF(OR(K61="",L61=""),"",L61-K61+1) -> 14 | N61: Not Started | O61: 0 | P61: T-028 | Q61: Monitor | R61: G5 | T61: =IF(OR(N61="Complete",N61="Deferred",L61=""),0,MAX(0,TODAY()-L61)) -> 0 | U61: =IF(N61="Complete","Done",IF(OR(N61="Blocked",T61>5),"Red",IF(OR(N61="At Risk",T61>0,AND(N61="Not Started",K61<TODAY())),"Amber","Green"))) -> Green
A62: T-058 | B62: 5. Integration & Testing | C62: PMO | D62: OBJ-02 | E62: Gate 5 Review | F62: Completeness Gate 5: SIT / UAT / performance / throughput exit criteria met, no open Sev-1 | G62: SH-02 | H62: SH-01 | I62: SH-10 | J62: SH-05 | K62: 46573 | L62: 46579 | M62: =IF(OR(K62="",L62=""),"",L62-K62+1) -> 7 | N62: Not Started | O62: 0 | P62: T-053,T-054,T-055 | Q62: Communicate | R62: G5 | T62: =IF(OR(N62="Complete",N62="Deferred",L62=""),0,MAX(0,TODAY()-L62)) -> 0 | U62: =IF(N62="Complete","Done",IF(OR(N62="Blocked",T62>5),"Red",IF(OR(N62="At Risk",T62>0,AND(N62="Not Started",K62<TODAY())),"Amber","Green"))) -> Green
A63: T-059 | B63: 6. Training & Change | C63: Change & Training | D63: OBJ-04 | E63: Training Content | F63: Build role-based training and job aids from SOPs | G63: SH-17 | H63: SH-17 | I63: SH-11 | J63: SH-05 | K63: 46510 | L63: 46544 | M63: =IF(OR(K63="",L63=""),"",L63-K63+1) -> 35 | N63: Not Started | O63: 0 | P63: T-035 | Q63: Monitor | R63: G6 | T63: =IF(OR(N63="Complete",N63="Deferred",L63=""),0,MAX(0,TODAY()-L63)) -> 0 | U63: =IF(N63="Complete","Done",IF(OR(N63="Blocked",T63>5),"Red",IF(OR(N63="At Risk",T63>0,AND(N63="Not Started",K63<TODAY())),"Amber","Green"))) -> Green
A64: T-060 | B64: 6. Training & Change | C64: Change & Training | D64: OBJ-04 | E64: Super-User Training | F64: Train and certify super-users (one per process area per shift) | G64: SH-17 | H64: SH-11 | I64: SH-05 | J64: SH-10 | K64: 46538 | L64: 46551 | M64: =IF(OR(K64="",L64=""),"",L64-K64+1) -> 14 | N64: Not Started | O64: 0 | P64: T-059,T-046 | Q64: Monitor | R64: G6 | T64: =IF(OR(N64="Complete",N64="Deferred",L64=""),0,MAX(0,TODAY()-L64)) -> 0 | U64: =IF(N64="Complete","Done",IF(OR(N64="Blocked",T64>5),"Red",IF(OR(N64="At Risk",T64>0,AND(N64="Not Started",K64<TODAY())),"Amber","Green"))) -> Green
A65: T-061 | B65: 6. Training & Change | C65: Operations & Staffing | D65: OBJ-04 | E65: Associate Hiring | F65: Hire go-live associate headcount | G65: SH-11 | H65: SH-11 | I65: SH-17 | J65: SH-16 | K65: 46510 | L65: 46565 | M65: =IF(OR(K65="",L65=""),"",L65-K65+1) -> 56 | N65: Not Started | O65: 0 | P65: T-036 | Q65: Monitor | R65: G6 | T65: =IF(OR(N65="Complete",N65="Deferred",L65=""),0,MAX(0,TODAY()-L65)) -> 0 | U65: =IF(N65="Complete","Done",IF(OR(N65="Blocked",T65>5),"Red",IF(OR(N65="At Risk",T65>0,AND(N65="Not Started",K65<TODAY())),"Amber","Green"))) -> Green
A66: T-062 | B66: 6. Training & Change | C66: Change & Training | D66: OBJ-04 | E66: Associate Training | F66: Train and certify all go-live associates (hands-on in TEST) | G66: SH-17 | H66: SH-11 | I66: SH-05 | J66: SH-15 | K66: 46566 | L66: 46586 | M66: =IF(OR(K66="",L66=""),"",L66-K66+1) -> 21 | N66: Not Started | O66: 0 | P66: T-060,T-061 | Q66: Monitor | R66: G6 | T66: =IF(OR(N66="Complete",N66="Deferred",L66=""),0,MAX(0,TODAY()-L66)) -> 0 | U66: =IF(N66="Complete","Done",IF(OR(N66="Blocked",T66>5),"Red",IF(OR(N66="At Risk",T66>0,AND(N66="Not Started",K66<TODAY())),"Amber","Green"))) -> Green
A67: T-063 | B67: 6. Training & Change | C67: Change & Training | D67: OBJ-06 | E67: Communications | F67: Stakeholder and customer / supplier go-live communications | G67: SH-17 | H67: SH-02 | I67: SH-12 | J67: SH-13 | K67: 46552 | L67: 46586 | M67: =IF(OR(K67="",L67=""),"",L67-K67+1) -> 35 | N67: Not Started | O67: 0 | P67: T-021 | Q67: Communicate | T67: =IF(OR(N67="Complete",N67="Deferred",L67=""),0,MAX(0,TODAY()-L67)) -> 0 | U67: =IF(N67="Complete","Done",IF(OR(N67="Blocked",T67>5),"Red",IF(OR(N67="At Risk",T67>0,AND(N67="Not Started",K67<TODAY())),"Amber","Green"))) -> Green
A68: T-064 | B68: 6. Training & Change | C68: Operations & Staffing | D68: OBJ-04 | E68: Operational Dress Rehearsal | F68: Simulated day-in-the-life with real equipment and system | G68: SH-11 | H68: SH-11 | I68: SH-07 | J68: SH-05 | K68: 46580 | L68: 46586 | M68: =IF(OR(K68="",L68=""),"",L68-K68+1) -> 7 | N68: Not Started | O68: 0 | P68: T-062,T-054 | Q68: Monitor | R68: G6 | T68: =IF(OR(N68="Complete",N68="Deferred",L68=""),0,MAX(0,TODAY()-L68)) -> 0 | U68: =IF(N68="Complete","Done",IF(OR(N68="Blocked",T68>5),"Red",IF(OR(N68="At Risk",T68>0,AND(N68="Not Started",K68<TODAY())),"Amber","Green"))) -> Green
A69: T-065 | B69: 6. Training & Change | C69: PMO | D69: OBJ-04 | E69: Gate 6 Review | F69: Completeness Gate 6: 100% training certified, rehearsal passed | G69: SH-02 | H69: SH-01 | I69: SH-17 | J69: SH-11 | K69: 46587 | L69: 46593 | M69: =IF(OR(K69="",L69=""),"",L69-K69+1) -> 7 | N69: Not Started | O69: 0 | P69: T-062,T-064 | Q69: Communicate | R69: G6 | T69: =IF(OR(N69="Complete",N69="Deferred",L69=""),0,MAX(0,TODAY()-L69)) -> 0 | U69: =IF(N69="Complete","Done",IF(OR(N69="Blocked",T69>5),"Red",IF(OR(N69="At Risk",T69>0,AND(N69="Not Started",K69<TODAY())),"Amber","Green"))) -> Green
A70: T-066 | B70: 7. Cutover & Go-Live | C70: Cutover & Go-Live | D70: OBJ-01 | E70: Cutover Runbook | F70: Minute-by-minute cutover runbook with owners and rollback plan | G70: SH-19 | H70: SH-02 | I70: SH-06 | J70: SH-11 | K70: 46566 | L70: 46579 | M70: =IF(OR(K70="",L70=""),"",L70-K70+1) -> 14 | N70: Not Started | O70: 0 | P70: T-058 | Q70: Plan | R70: G7 | T70: =IF(OR(N70="Complete",N70="Deferred",L70=""),0,MAX(0,TODAY()-L70)) -> 0 | U70: =IF(N70="Complete","Done",IF(OR(N70="Blocked",T70>5),"Red",IF(OR(N70="At Risk",T70>0,AND(N70="Not Started",K70<TODAY())),"Amber","Green"))) -> Green
A71: T-067 | B71: 7. Cutover & Go-Live | C71: Cutover & Go-Live | D71: OBJ-01 | E71: Cutover Rehearsal | F71: Full cutover rehearsal in TEST including data load timing | G71: SH-19 | H71: SH-19 | I71: SH-09 | J71: SH-08 | K71: 46580 | L71: 46586 | M71: =IF(OR(K71="",L71=""),"",L71-K71+1) -> 7 | N71: Not Started | O71: 0 | P71: T-066,T-052 | Q71: Monitor | R71: G7 | T71: =IF(OR(N71="Complete",N71="Deferred",L71=""),0,MAX(0,TODAY()-L71)) -> 0 | U71: =IF(N71="Complete","Done",IF(OR(N71="Blocked",T71>5),"Red",IF(OR(N71="At Risk",T71>0,AND(N71="Not Started",K71<TODAY())),"Amber","Green"))) -> Green
A72: T-068 | B72: 7. Cutover & Go-Live | C72: Cutover & Go-Live | D72: OBJ-01 | E72: Go / No-Go Readiness | F72: Readiness assessment across all workstreams; sponsor decision | G72: SH-19 | H72: SH-01 | I72: SH-02 | J72: SH-11 | K72: 46594 | L72: 46600 | M72: =IF(OR(K72="",L72=""),"",L72-K72+1) -> 7 | N72: Not Started | O72: 0 | P72: T-058,T-065,T-067 | Q72: Communicate | R72: G7 | T72: =IF(OR(N72="Complete",N72="Deferred",L72=""),0,MAX(0,TODAY()-L72)) -> 0 | U72: =IF(N72="Complete","Done",IF(OR(N72="Blocked",T72>5),"Red",IF(OR(N72="At Risk",T72>0,AND(N72="Not Started",K72<TODAY())),"Amber","Green"))) -> Green
A73: T-069 | B73: 7. Cutover & Go-Live | C73: Integration & Data | D73: OBJ-02 | E73: Production Data Load | F73: Final data migration into PROD with reconciliation sign-off | G73: SH-09 | H73: SH-08 | I73: SH-06 | J73: SH-11 | K73: 46601 | L73: 46607 | M73: =IF(OR(K73="",L73=""),"",L73-K73+1) -> 7 | N73: Not Started | O73: 0 | P73: T-068 | Q73: Monitor | R73: G7 | T73: =IF(OR(N73="Complete",N73="Deferred",L73=""),0,MAX(0,TODAY()-L73)) -> 0 | U73: =IF(N73="Complete","Done",IF(OR(N73="Blocked",T73>5),"Red",IF(OR(N73="At Risk",T73>0,AND(N73="Not Started",K73<TODAY())),"Amber","Green"))) -> Green
A74: T-070 | B74: 7. Cutover & Go-Live | C74: WMS / WCS | D74: OBJ-02 | E74: Production Code Deploy | F74: Deploy WMS / interfaces to PROD; smoke test | G74: SH-06 | H74: SH-05 | I74: SH-18 | J74: SH-19 | K74: 46601 | L74: 46607 | M74: =IF(OR(K74="",L74=""),"",L74-K74+1) -> 7 | N74: Not Started | O74: 0 | P74: T-068 | Q74: Monitor | R74: G7 | T74: =IF(OR(N74="Complete",N74="Deferred",L74=""),0,MAX(0,TODAY()-L74)) -> 0 | U74: =IF(N74="Complete","Done",IF(OR(N74="Blocked",T74>5),"Red",IF(OR(N74="At Risk",T74>0,AND(N74="Not Started",K74<TODAY())),"Amber","Green"))) -> Green
A75: T-071 | B75: 7. Cutover & Go-Live | C75: Cutover & Go-Live | D75: OBJ-01 | E75: Command Center | F75: Stand up go-live command center and escalation rota | G75: SH-19 | H75: SH-02 | I75: SH-20 | J75: SH-11 | K75: 46601 | L75: 46614 | M75: =IF(OR(K75="",L75=""),"",L75-K75+1) -> 14 | N75: Not Started | O75: 0 | P75: T-068 | Q75: Communicate | T75: =IF(OR(N75="Complete",N75="Deferred",L75=""),0,MAX(0,TODAY()-L75)) -> 0 | U75: =IF(N75="Complete","Done",IF(OR(N75="Blocked",T75>5),"Red",IF(OR(N75="At Risk",T75>0,AND(N75="Not Started",K75<TODAY())),"Amber","Green"))) -> Green
A76: T-072 | B76: 7. Cutover & Go-Live | C76: Operations & Staffing | D76: OBJ-06 | E76: First Inbound Receipt | F76: Execute first inbound receipt and putaway in production | G76: SH-11 | H76: SH-11 | I76: SH-12 | J76: SH-05 | K76: 46608 | L76: 46614 | M76: =IF(OR(K76="",L76=""),"",L76-K76+1) -> 7 | N76: Not Started | O76: 0 | P76: T-069,T-070 | Q76: Monitor | R76: G7 | T76: =IF(OR(N76="Complete",N76="Deferred",L76=""),0,MAX(0,TODAY()-L76)) -> 0 | U76: =IF(N76="Complete","Done",IF(OR(N76="Blocked",T76>5),"Red",IF(OR(N76="At Risk",T76>0,AND(N76="Not Started",K76<TODAY())),"Amber","Green"))) -> Green
A77: T-073 | B77: 7. Cutover & Go-Live | C77: Operations & Staffing | D77: OBJ-06 | E77: First Outbound Shipment | F77: Execute first pick, pack, ship and carrier tender | G77: SH-11 | H77: SH-11 | I77: SH-12 | J77: SH-05 | K77: 46608 | L77: 46614 | M77: =IF(OR(K77="",L77=""),"",L77-K77+1) -> 7 | N77: Not Started | O77: 0 | P77: T-072 | Q77: Monitor | R77: G7 | T77: =IF(OR(N77="Complete",N77="Deferred",L77=""),0,MAX(0,TODAY()-L77)) -> 0 | U77: =IF(N77="Complete","Done",IF(OR(N77="Blocked",T77>5),"Red",IF(OR(N77="At Risk",T77>0,AND(N77="Not Started",K77<TODAY())),"Amber","Green"))) -> Green
A78: T-074 | B78: 7. Cutover & Go-Live | C78: PMO | D78: OBJ-01 | E78: Gate 7 Review | F78: Completeness Gate 7: production go-live achieved, first shipments confirmed | G78: SH-02 | H78: SH-01 | I78: SH-19 | J78: SH-11 | K78: 46608 | L78: 46614 | M78: =IF(OR(K78="",L78=""),"",L78-K78+1) -> 7 | N78: Not Started | O78: 0 | P78: T-072,T-073 | Q78: Communicate | R78: G7 | T78: =IF(OR(N78="Complete",N78="Deferred",L78=""),0,MAX(0,TODAY()-L78)) -> 0 | U78: =IF(N78="Complete","Done",IF(OR(N78="Blocked",T78>5),"Red",IF(OR(N78="At Risk",T78>0,AND(N78="Not Started",K78<TODAY())),"Amber","Green"))) -> Green
A79: T-075 | B79: 8. Hypercare & Close | C79: Hypercare & Close | D79: OBJ-08 | E79: Hypercare Support | F79: Daily stabilisation review: defects, throughput, inventory accuracy | G79: SH-20 | H79: SH-20 | I79: SH-11 | J79: SH-05 | K79: 46608 | L79: 46649 | M79: =IF(OR(K79="",L79=""),"",L79-K79+1) -> 42 | N79: Not Started | O79: 0 | P79: T-074 | Q79: Monitor | T79: =IF(OR(N79="Complete",N79="Deferred",L79=""),0,MAX(0,TODAY()-L79)) -> 0 | U79: =IF(N79="Complete","Done",IF(OR(N79="Blocked",T79>5),"Red",IF(OR(N79="At Risk",T79>0,AND(N79="Not Started",K79<TODAY())),"Amber","Green"))) -> Green
A80: T-076 | B80: 8. Hypercare & Close | C80: Hypercare & Close | D80: OBJ-03 | E80: Volume Ramp | F80: Ramp to planned volume against ramp curve | G80: SH-11 | H80: SH-11 | I80: SH-07 | J80: SH-12 | K80: 46615 | L80: 46656 | M80: =IF(OR(K80="",L80=""),"",L80-K80+1) -> 42 | N80: Not Started | O80: 0 | P80: T-074 | Q80: Monitor | R80: G8 | T80: =IF(OR(N80="Complete",N80="Deferred",L80=""),0,MAX(0,TODAY()-L80)) -> 0 | U80: =IF(N80="Complete","Done",IF(OR(N80="Blocked",T80>5),"Red",IF(OR(N80="At Risk",T80>0,AND(N80="Not Started",K80<TODAY())),"Amber","Green"))) -> Green
A81: T-077 | B81: 8. Hypercare & Close | C81: Finance | D81: OBJ-07 | E81: Financial Close | F81: Final capex reconciliation and benefits baseline | G81: SH-16 | H81: SH-16 | I81: SH-02 | J81: SH-01 | K81: 46636 | L81: 46656 | M81: =IF(OR(K81="",L81=""),"",L81-K81+1) -> 21 | N81: Not Started | O81: 0 | P81: T-038 | Q81: Close | R81: G8 | T81: =IF(OR(N81="Complete",N81="Deferred",L81=""),0,MAX(0,TODAY()-L81)) -> 0 | U81: =IF(N81="Complete","Done",IF(OR(N81="Blocked",T81>5),"Red",IF(OR(N81="At Risk",T81>0,AND(N81="Not Started",K81<TODAY())),"Amber","Green"))) -> Green
A82: T-078 | B82: 8. Hypercare & Close | C82: Vendors | D82: OBJ-03 | E82: Vendor Acceptance | F82: Final acceptance certificates and warranty start for MHE / WMS | G82: SH-13 | H82: SH-07 | I82: SH-14 | J82: SH-16 | K82: 46636 | L82: 46649 | M82: =IF(OR(K82="",L82=""),"",L82-K82+1) -> 14 | N82: Not Started | O82: 0 | P82: T-054 | Q82: Close | R82: G8 | T82: =IF(OR(N82="Complete",N82="Deferred",L82=""),0,MAX(0,TODAY()-L82)) -> 0 | U82: =IF(N82="Complete","Done",IF(OR(N82="Blocked",T82>5),"Red",IF(OR(N82="At Risk",T82>0,AND(N82="Not Started",K82<TODAY())),"Amber","Green"))) -> Green
A83: T-079 | B83: 8. Hypercare & Close | C83: Hypercare & Close | D83: OBJ-08 | E83: Handover to Run | F83: Transition to run support; knowledge transfer complete | G83: SH-20 | H83: SH-20 | I83: SH-06 | J83: SH-11 | K83: 46650 | L83: 46656 | M83: =IF(OR(K83="",L83=""),"",L83-K83+1) -> 7 | N83: Not Started | O83: 0 | P83: T-075 | Q83: Close | R83: G8 | T83: =IF(OR(N83="Complete",N83="Deferred",L83=""),0,MAX(0,TODAY()-L83)) -> 0 | U83: =IF(N83="Complete","Done",IF(OR(N83="Blocked",T83>5),"Red",IF(OR(N83="At Risk",T83>0,AND(N83="Not Started",K83<TODAY())),"Amber","Green"))) -> Green
A84: T-080 | B84: 8. Hypercare & Close | C84: PMO | D84: OBJ-08 | E84: Lessons Learned | F84: AI-summarised lessons learned from RAID log and status history; templates updated | G84: SH-02 | H84: SH-02 | I84: SH-11 | J84: SH-01 | K84: 46650 | L84: 46656 | M84: =IF(OR(K84="",L84=""),"",L84-K84+1) -> 7 | N84: Not Started | O84: 0 | P84: T-075 | Q84: Close | R84: G8 | T84: =IF(OR(N84="Complete",N84="Deferred",L84=""),0,MAX(0,TODAY()-L84)) -> 0 | U84: =IF(N84="Complete","Done",IF(OR(N84="Blocked",T84>5),"Red",IF(OR(N84="At Risk",T84>0,AND(N84="Not Started",K84<TODAY())),"Amber","Green"))) -> Green
A85: T-081 | B85: 8. Hypercare & Close | C85: PMO | D85: OBJ-08 | E85: Gate 8 Review | F85: Completeness Gate 8: hypercare exit, financial close, lessons published, project archived | G85: SH-02 | H85: SH-01 | I85: SH-20 | J85: SH-16 | K85: 46657 | L85: 46663 | M85: =IF(OR(K85="",L85=""),"",L85-K85+1) -> 7 | N85: Not Started | O85: 0 | P85: T-076,T-077,T-079,T-080 | Q85: Close | R85: G8 | T85: =IF(OR(N85="Complete",N85="Deferred",L85=""),0,MAX(0,TODAY()-L85)) -> 0 | U85: =IF(N85="Complete","Done",IF(OR(N85="Blocked",T85>5),"Red",IF(OR(N85="At Risk",T85>0,AND(N85="Not Started",K85<TODAY())),"Amber","Green"))) -> Green

Sheet RACI Matrix
A1: RACI Traceability Matrix — every stakeholder against every task (auto-derived from Master Plan)
A2: Formula-driven: R = Responsible, A = Accountable, C = Consulted, I = Informed. Edit assignments in Master Plan columns G–J, not here. Totals at right show each stakeholder's load.
D3: Stakeholder ID → | E3: SH-01 | F3: SH-02 | G3: SH-03 | H3: SH-04 | I3: SH-05 | J3: SH-06 | K3: SH-07 | L3: SH-08 | M3: SH-09 | N3: SH-10 | O3: SH-11 | P3: SH-12 | Q3: SH-13 | R3: SH-14 | S3: SH-15 | T3: SH-16 | U3: SH-17 | V3: SH-18 | W3: SH-19 | X3: SH-20
A4: Task ID | B4: Phase | C4: Deliverable | D4: Status | E4: Executive Sponsor | F4: Program Manager | G4: PMO Analyst | H4: Site / Facilities Lead | I4: WMS Product Owner | J4: WMS Tech Lead | K4: WCS / Automation Lead | L4: Integration / ERP Lead | M4: Data Migration Lead | N4: QA / Test Manager | O4: Operations Lead | P4: Transportation Lead | Q4: Procurement / Vendor Lead | R4: MHE Vendor PM | S4: Safety & Compliance Lead | T4: Finance Partner | U4: Change & Training Lead | V4: IT Infrastructure Lead | W4: Cutover Manager | X4: Hypercare Lead | Y4: # R | Z4: # A | AA4: # C | AB4: # I
A5: ='Master Plan'!A5 -> T-001 | B5: ='Master Plan'!B5 -> 1. Initiation | C5: ='Master Plan'!E5 -> Project Charter | D5: ='Master Plan'!N5 -> Complete | E5: =IF('Master Plan'!$G5=E$3,"R",IF('Master Plan'!$H5=E$3,"A",IF('Master Plan'!$I5=E$3,"C",IF('Master Plan'!$J5=E$3,"I","")))) -> A | F5: =IF('Master Plan'!$G5=F$3,"R",IF('Master Plan'!$H5=F$3,"A",IF('Master Plan'!$I5=F$3,"C",IF('Master Plan'!$J5=F$3,"I","")))) -> R | G5: =IF('Master Plan'!$G5=G$3,"R",IF('Master Plan'!$H5=G$3,"A",IF('Master Plan'!$I5=G$3,"C",IF('Master Plan'!$J5=G$3,"I","")))) | H5: =IF('Master Plan'!$G5=H$3,"R",IF('Master Plan'!$H5=H$3,"A",IF('Master Plan'!$I5=H$3,"C",IF('Master Plan'!$J5=H$3,"I","")))) | I5: =IF('Master Plan'!$G5=I$3,"R",IF('Master Plan'!$H5=I$3,"A",IF('Master Plan'!$I5=I$3,"C",IF('Master Plan'!$J5=I$3,"I","")))) | J5: =IF('Master Plan'!$G5=J$3,"R",IF('Master Plan'!$H5=J$3,"A",IF('Master Plan'!$I5=J$3,"C",IF('Master Plan'!$J5=J$3,"I","")))) | K5: =IF('Master Plan'!$G5=K$3,"R",IF('Master Plan'!$H5=K$3,"A",IF('Master Plan'!$I5=K$3,"C",IF('Master Plan'!$J5=K$3,"I","")))) | L5: =IF('Master Plan'!$G5=L$3,"R",IF('Master Plan'!$H5=L$3,"A",IF('Master Plan'!$I5=L$3,"C",IF('Master Plan'!$J5=L$3,"I","")))) | ... X5: =IF('Master Plan'!$G5=X$3,"R",IF('Master Plan'!$H5=X$3,"A",IF('Master Plan'!$I5=X$3,"C",IF('Master Plan'!$J5=X$3,"I","")))) | Y5: =COUNTIF(E5:X5,"R") -> 1 | Z5: =COUNTIF(E5:X5,"A") -> 1 | AA5: =COUNTIF(E5:X5,"C") -> 1 | AB5: =COUNTIF(E5:X5,"I") -> 1
A6: ='Master Plan'!A6 -> T-002 | B6: ='Master Plan'!B6 -> 1. Initiation | C6: ='Master Plan'!E6 -> Project Charter | D6: ='Master Plan'!N6 -> Complete | E6: =IF('Master Plan'!$G6=E$3,"R",IF('Master Plan'!$H6=E$3,"A",IF('Master Plan'!$I6=E$3,"C",IF('Master Plan'!$J6=E$3,"I","")))) -> R | F6: =IF('Master Plan'!$G6=F$3,"R",IF('Master Plan'!$H6=F$3,"A",IF('Master Plan'!$I6=F$3,"C",IF('Master Plan'!$J6=F$3,"I","")))) -> C | G6: =IF('Master Plan'!$G6=G$3,"R",IF('Master Plan'!$H6=G$3,"A",IF('Master Plan'!$I6=G$3,"C",IF('Master Plan'!$J6=G$3,"I","")))) -> I | H6: =IF('Master Plan'!$G6=H$3,"R",IF('Master Plan'!$H6=H$3,"A",IF('Master Plan'!$I6=H$3,"C",IF('Master Plan'!$J6=H$3,"I","")))) | I6: =IF('Master Plan'!$G6=I$3,"R",IF('Master Plan'!$H6=I$3,"A",IF('Master Plan'!$I6=I$3,"C",IF('Master Plan'!$J6=I$3,"I","")))) | J6: =IF('Master Plan'!$G6=J$3,"R",IF('Master Plan'!$H6=J$3,"A",IF('Master Plan'!$I6=J$3,"C",IF('Master Plan'!$J6=J$3,"I","")))) | K6: =IF('Master Plan'!$G6=K$3,"R",IF('Master Plan'!$H6=K$3,"A",IF('Master Plan'!$I6=K$3,"C",IF('Master Plan'!$J6=K$3,"I","")))) | L6: =IF('Master Plan'!$G6=L$3,"R",IF('Master Plan'!$H6=L$3,"A",IF('Master Plan'!$I6=L$3,"C",IF('Master Plan'!$J6=L$3,"I","")))) | ... X6: =IF('Master Plan'!$G6=X$3,"R",IF('Master Plan'!$H6=X$3,"A",IF('Master Plan'!$I6=X$3,"C",IF('Master Plan'!$J6=X$3,"I","")))) | Y6: =COUNTIF(E6:X6,"R") -> 1 | Z6: =COUNTIF(E6:X6,"A") -> 0 | AA6: =COUNTIF(E6:X6,"C") -> 1 | AB6: =COUNTIF(E6:X6,"I") -> 1
A7: ='Master Plan'!A7 -> T-003 | B7: ='Master Plan'!B7 -> 1. Initiation | C7: ='Master Plan'!E7 -> Stakeholder Register | D7: ='Master Plan'!N7 -> Complete | E7: =IF('Master Plan'!$G7=E$3,"R",IF('Master Plan'!$H7=E$3,"A",IF('Master Plan'!$I7=E$3,"C",IF('Master Plan'!$J7=E$3,"I","")))) -> A | F7: =IF('Master Plan'!$G7=F$3,"R",IF('Master Plan'!$H7=F$3,"A",IF('Master Plan'!$I7=F$3,"C",IF('Master Plan'!$J7=F$3,"I","")))) -> R | G7: =IF('Master Plan'!$G7=G$3,"R",IF('Master Plan'!$H7=G$3,"A",IF('Master Plan'!$I7=G$3,"C",IF('Master Plan'!$J7=G$3,"I","")))) -> I | H7: =IF('Master Plan'!$G7=H$3,"R",IF('Master Plan'!$H7=H$3,"A",IF('Master Plan'!$I7=H$3,"C",IF('Master Plan'!$J7=H$3,"I","")))) | I7: =IF('Master Plan'!$G7=I$3,"R",IF('Master Plan'!$H7=I$3,"A",IF('Master Plan'!$I7=I$3,"C",IF('Master Plan'!$J7=I$3,"I","")))) | J7: =IF('Master Plan'!$G7=J$3,"R",IF('Master Plan'!$H7=J$3,"A",IF('Master Plan'!$I7=J$3,"C",IF('Master Plan'!$J7=J$3,"I","")))) | K7: =IF('Master Plan'!$G7=K$3,"R",IF('Master Plan'!$H7=K$3,"A",IF('Master Plan'!$I7=K$3,"C",IF('Master Plan'!$J7=K$3,"I","")))) | L7: =IF('Master Plan'!$G7=L$3,"R",IF('Master Plan'!$H7=L$3,"A",IF('Master Plan'!$I7=L$3,"C",IF('Master Plan'!$J7=L$3,"I","")))) | ... X7: =IF('Master Plan'!$G7=X$3,"R",IF('Master Plan'!$H7=X$3,"A",IF('Master Plan'!$I7=X$3,"C",IF('Master Plan'!$J7=X$3,"I","")))) | Y7: =COUNTIF(E7:X7,"R") -> 1 | Z7: =COUNTIF(E7:X7,"A") -> 1 | AA7: =COUNTIF(E7:X7,"C") -> 1 | AB7: =COUNTIF(E7:X7,"I") -> 1
A8: ='Master Plan'!A8 -> T-004 | B8: ='Master Plan'!B8 -> 1. Initiation | C8: ='Master Plan'!E8 -> Budget Baseline | D8: ='Master Plan'!N8 -> Complete | E8: =IF('Master Plan'!$G8=E$3,"R",IF('Master Plan'!$H8=E$3,"A",IF('Master Plan'!$I8=E$3,"C",IF('Master Plan'!$J8=E$3,"I","")))) -> A | F8: =IF('Master Plan'!$G8=F$3,"R",IF('Master Plan'!$H8=F$3,"A",IF('Master Plan'!$I8=F$3,"C",IF('Master Plan'!$J8=F$3,"I","")))) -> C | G8: =IF('Master Plan'!$G8=G$3,"R",IF('Master Plan'!$H8=G$3,"A",IF('Master Plan'!$I8=G$3,"C",IF('Master Plan'!$J8=G$3,"I","")))) | H8: =IF('Master Plan'!$G8=H$3,"R",IF('Master Plan'!$H8=H$3,"A",IF('Master Plan'!$I8=H$3,"C",IF('Master Plan'!$J8=H$3,"I","")))) | I8: =IF('Master Plan'!$G8=I$3,"R",IF('Master Plan'!$H8=I$3,"A",IF('Master Plan'!$I8=I$3,"C",IF('Master Plan'!$J8=I$3,"I","")))) | J8: =IF('Master Plan'!$G8=J$3,"R",IF('Master Plan'!$H8=J$3,"A",IF('Master Plan'!$I8=J$3,"C",IF('Master Plan'!$J8=J$3,"I","")))) | K8: =IF('Master Plan'!$G8=K$3,"R",IF('Master Plan'!$H8=K$3,"A",IF('Master Plan'!$I8=K$3,"C",IF('Master Plan'!$J8=K$3,"I","")))) | L8: =IF('Master Plan'!$G8=L$3,"R",IF('Master Plan'!$H8=L$3,"A",IF('Master Plan'!$I8=L$3,"C",IF('Master Plan'!$J8=L$3,"I","")))) | ... X8: =IF('Master Plan'!$G8=X$3,"R",IF('Master Plan'!$H8=X$3,"A",IF('Master Plan'!$I8=X$3,"C",IF('Master Plan'!$J8=X$3,"I","")))) | Y8: =COUNTIF(E8:X8,"R") -> 1 | Z8: =COUNTIF(E8:X8,"A") -> 1 | AA8: =COUNTIF(E8:X8,"C") -> 1 | AB8: =COUNTIF(E8:X8,"I") -> 1
A9: ='Master Plan'!A9 -> T-005 | B9: ='Master Plan'!B9 -> 1. Initiation | C9: ='Master Plan'!E9 -> Governance Model | D9: ='Master Plan'!N9 -> Complete | E9: =IF('Master Plan'!$G9=E$3,"R",IF('Master Plan'!$H9=E$3,"A",IF('Master Plan'!$I9=E$3,"C",IF('Master Plan'!$J9=E$3,"I","")))) -> A | F9: =IF('Master Plan'!$G9=F$3,"R",IF('Master Plan'!$H9=F$3,"A",IF('Master Plan'!$I9=F$3,"C",IF('Master Plan'!$J9=F$3,"I","")))) -> R | G9: =IF('Master Plan'!$G9=G$3,"R",IF('Master Plan'!$H9=G$3,"A",IF('Master Plan'!$I9=G$3,"C",IF('Master Plan'!$J9=G$3,"I","")))) -> C | H9: =IF('Master Plan'!$G9=H$3,"R",IF('Master Plan'!$H9=H$3,"A",IF('Master Plan'!$I9=H$3,"C",IF('Master Plan'!$J9=H$3,"I","")))) | I9: =IF('Master Plan'!$G9=I$3,"R",IF('Master Plan'!$H9=I$3,"A",IF('Master Plan'!$I9=I$3,"C",IF('Master Plan'!$J9=I$3,"I","")))) | J9: =IF('Master Plan'!$G9=J$3,"R",IF('Master Plan'!$H9=J$3,"A",IF('Master Plan'!$I9=J$3,"C",IF('Master Plan'!$J9=J$3,"I","")))) | K9: =IF('Master Plan'!$G9=K$3,"R",IF('Master Plan'!$H9=K$3,"A",IF('Master Plan'!$I9=K$3,"C",IF('Master Plan'!$J9=K$3,"I","")))) | L9: =IF('Master Plan'!$G9=L$3,"R",IF('Master Plan'!$H9=L$3,"A",IF('Master Plan'!$I9=L$3,"C",IF('Master Plan'!$J9=L$3,"I","")))) | ... X9: =IF('Master Plan'!$G9=X$3,"R",IF('Master Plan'!$H9=X$3,"A",IF('Master Plan'!$I9=X$3,"C",IF('Master Plan'!$J9=X$3,"I","")))) | Y9: =COUNTIF(E9:X9,"R") -> 1 | Z9: =COUNTIF(E9:X9,"A") -> 1 | AA9: =COUNTIF(E9:X9,"C") -> 1 | AB9: =COUNTIF(E9:X9,"I") -> 1
A10: ='Master Plan'!A10 -> T-006 | B10: ='Master Plan'!B10 -> 1. Initiation | C10: ='Master Plan'!E10 -> Vendor Shortlist | D10: ='Master Plan'!N10 -> In Progress | E10: =IF('Master Plan'!$G10=E$3,"R",IF('Master Plan'!$H10=E$3,"A",IF('Master Plan'!$I10=E$3,"C",IF('Master Plan'!$J10=E$3,"I","")))) | F10: =IF('Master Plan'!$G10=F$3,"R",IF('Master Plan'!$H10=F$3,"A",IF('Master Plan'!$I10=F$3,"C",IF('Master Plan'!$J10=F$3,"I","")))) -> A | G10: =IF('Master Plan'!$G10=G$3,"R",IF('Master Plan'!$H10=G$3,"A",IF('Master Plan'!$I10=G$3,"C",IF('Master Plan'!$J10=G$3,"I","")))) | H10: =IF('Master Plan'!$G10=H$3,"R",IF('Master Plan'!$H10=H$3,"A",IF('Master Plan'!$I10=H$3,"C",IF('Master Plan'!$J10=H$3,"I","")))) | I10: =IF('Master Plan'!$G10=I$3,"R",IF('Master Plan'!$H10=I$3,"A",IF('Master Plan'!$I10=I$3,"C",IF('Master Plan'!$J10=I$3,"I","")))) | J10: =IF('Master Plan'!$G10=J$3,"R",IF('Master Plan'!$H10=J$3,"A",IF('Master Plan'!$I10=J$3,"C",IF('Master Plan'!$J10=J$3,"I","")))) | K10: =IF('Master Plan'!$G10=K$3,"R",IF('Master Plan'!$H10=K$3,"A",IF('Master Plan'!$I10=K$3,"C",IF('Master Plan'!$J10=K$3,"I","")))) -> C | L10: =IF('Master Plan'!$G10=L$3,"R",IF('Master Plan'!$H10=L$3,"A",IF('Master Plan'!$I10=L$3,"C",IF('Master Plan'!$J10=L$3,"I","")))) | ... X10: =IF('Master Plan'!$G10=X$3,"R",IF('Master Plan'!$H10=X$3,"A",IF('Master Plan'!$I10=X$3,"C",IF('Master Plan'!$J10=X$3,"I","")))) | Y10: =COUNTIF(E10:X10,"R") -> 1 | Z10: =COUNTIF(E10:X10,"A") -> 1 | AA10: =COUNTIF(E10:X10,"C") -> 1 | AB10: =COUNTIF(E10:X10,"I") -> 1
A11: ='Master Plan'!A11 -> T-007 | B11: ='Master Plan'!B11 -> 1. Initiation | C11: ='Master Plan'!E11 -> Gate 1 Review | D11: ='Master Plan'!N11 -> In Progress | E11: =IF('Master Plan'!$G11=E$3,"R",IF('Master Plan'!$H11=E$3,"A",IF('Master Plan'!$I11=E$3,"C",IF('Master Plan'!$J11=E$3,"I","")))) -> A | F11: =IF('Master Plan'!$G11=F$3,"R",IF('Master Plan'!$H11=F$3,"A",IF('Master Plan'!$I11=F$3,"C",IF('Master Plan'!$J11=F$3,"I","")))) -> R | G11: =IF('Master Plan'!$G11=G$3,"R",IF('Master Plan'!$H11=G$3,"A",IF('Master Plan'!$I11=G$3,"C",IF('Master Plan'!$J11=G$3,"I","")))) -> C | H11: =IF('Master Plan'!$G11=H$3,"R",IF('Master Plan'!$H11=H$3,"A",IF('Master Plan'!$I11=H$3,"C",IF('Master Plan'!$J11=H$3,"I","")))) | I11: =IF('Master Plan'!$G11=I$3,"R",IF('Master Plan'!$H11=I$3,"A",IF('Master Plan'!$I11=I$3,"C",IF('Master Plan'!$J11=I$3,"I","")))) | J11: =IF('Master Plan'!$G11=J$3,"R",IF('Master Plan'!$H11=J$3,"A",IF('Master Plan'!$I11=J$3,"C",IF('Master Plan'!$J11=J$3,"I","")))) | K11: =IF('Master Plan'!$G11=K$3,"R",IF('Master Plan'!$H11=K$3,"A",IF('Master Plan'!$I11=K$3,"C",IF('Master Plan'!$J11=K$3,"I","")))) | L11: =IF('Master Plan'!$G11=L$3,"R",IF('Master Plan'!$H11=L$3,"A",IF('Master Plan'!$I11=L$3,"C",IF('Master Plan'!$J11=L$3,"I","")))) | ... X11: =IF('Master Plan'!$G11=X$3,"R",IF('Master Plan'!$H11=X$3,"A",IF('Master Plan'!$I11=X$3,"C",IF('Master Plan'!$J11=X$3,"I","")))) | Y11: =COUNTIF(E11:X11,"R") -> 1 | Z11: =COUNTIF(E11:X11,"A") -> 1 | AA11: =COUNTIF(E11:X11,"C") -> 1 | AB11: =COUNTIF(E11:X11,"I") -> 1
A12: ='Master Plan'!A12 -> T-008 | B12: ='Master Plan'!B12 -> 2. Planning & Design | C12: ='Master Plan'!E12 -> Integrated Master Plan | D12: ='Master Plan'!N12 -> In Progress | E12: =IF('Master Plan'!$G12=E$3,"R",IF('Master Plan'!$H12=E$3,"A",IF('Master Plan'!$I12=E$3,"C",IF('Master Plan'!$J12=E$3,"I","")))) -> A | F12: =IF('Master Plan'!$G12=F$3,"R",IF('Master Plan'!$H12=F$3,"A",IF('Master Plan'!$I12=F$3,"C",IF('Master Plan'!$J12=F$3,"I","")))) -> R | G12: =IF('Master Plan'!$G12=G$3,"R",IF('Master Plan'!$H12=G$3,"A",IF('Master Plan'!$I12=G$3,"C",IF('Master Plan'!$J12=G$3,"I","")))) | H12: =IF('Master Plan'!$G12=H$3,"R",IF('Master Plan'!$H12=H$3,"A",IF('Master Plan'!$I12=H$3,"C",IF('Master Plan'!$J12=H$3,"I","")))) | I12: =IF('Master Plan'!$G12=I$3,"R",IF('Master Plan'!$H12=I$3,"A",IF('Master Plan'!$I12=I$3,"C",IF('Master Plan'!$J12=I$3,"I","")))) -> C | J12: =IF('Master Plan'!$G12=J$3,"R",IF('Master Plan'!$H12=J$3,"A",IF('Master Plan'!$I12=J$3,"C",IF('Master Plan'!$J12=J$3,"I","")))) | K12: =IF('Master Plan'!$G12=K$3,"R",IF('Master Plan'!$H12=K$3,"A",IF('Master Plan'!$I12=K$3,"C",IF('Master Plan'!$J12=K$3,"I","")))) | L12: =IF('Master Plan'!$G12=L$3,"R",IF('Master Plan'!$H12=L$3,"A",IF('Master Plan'!$I12=L$3,"C",IF('Master Plan'!$J12=L$3,"I","")))) | ... X12: =IF('Master Plan'!$G12=X$3,"R",IF('Master Plan'!$H12=X$3,"A",IF('Master Plan'!$I12=X$3,"C",IF('Master Plan'!$J12=X$3,"I","")))) | Y12: =COUNTIF(E12:X12,"R") -> 1 | Z12: =COUNTIF(E12:X12,"A") -> 1 | AA12: =COUNTIF(E12:X12,"C") -> 1 | AB12: =COUNTIF(E12:X12,"I") -> 1
A13: ='Master Plan'!A13 -> T-009 | B13: ='Master Plan'!B13 -> 2. Planning & Design | C13: ='Master Plan'!E13 -> RAID Baseline | D13: ='Master Plan'!N13 -> Not Started | E13: =IF('Master Plan'!$G13=E$3,"R",IF('Master Plan'!$H13=E$3,"A",IF('Master Plan'!$I13=E$3,"C",IF('Master Plan'!$J13=E$3,"I","")))) -> I | F13: =IF('Master Plan'!$G13=F$3,"R",IF('Master Plan'!$H13=F$3,"A",IF('Master Plan'!$I13=F$3,"C",IF('Master Plan'!$J13=F$3,"I","")))) -> R | G13: =IF('Master Plan'!$G13=G$3,"R",IF('Master Plan'!$H13=G$3,"A",IF('Master Plan'!$I13=G$3,"C",IF('Master Plan'!$J13=G$3,"I","")))) | H13: =IF('Master Plan'!$G13=H$3,"R",IF('Master Plan'!$H13=H$3,"A",IF('Master Plan'!$I13=H$3,"C",IF('Master Plan'!$J13=H$3,"I","")))) | I13: =IF('Master Plan'!$G13=I$3,"R",IF('Master Plan'!$H13=I$3,"A",IF('Master Plan'!$I13=I$3,"C",IF('Master Plan'!$J13=I$3,"I","")))) -> C | J13: =IF('Master Plan'!$G13=J$3,"R",IF('Master Plan'!$H13=J$3,"A",IF('Master Plan'!$I13=J$3,"C",IF('Master Plan'!$J13=J$3,"I","")))) | K13: =IF('Master Plan'!$G13=K$3,"R",IF('Master Plan'!$H13=K$3,"A",IF('Master Plan'!$I13=K$3,"C",IF('Master Plan'!$J13=K$3,"I","")))) | L13: =IF('Master Plan'!$G13=L$3,"R",IF('Master Plan'!$H13=L$3,"A",IF('Master Plan'!$I13=L$3,"C",IF('Master Plan'!$J13=L$3,"I","")))) | ... X13: =IF('Master Plan'!$G13=X$3,"R",IF('Master Plan'!$H13=X$3,"A",IF('Master Plan'!$I13=X$3,"C",IF('Master Plan'!$J13=X$3,"I","")))) | Y13: =COUNTIF(E13:X13,"R") -> 1 | Z13: =COUNTIF(E13:X13,"A") -> 0 | AA13: =COUNTIF(E13:X13,"C") -> 1 | AB13: =COUNTIF(E13:X13,"I") -> 1
A14: ='Master Plan'!A14 -> T-010 | B14: ='Master Plan'!B14 -> 2. Planning & Design | C14: ='Master Plan'!E14 -> Facility Design | D14: ='Master Plan'!N14 -> Not Started | E14: =IF('Master Plan'!$G14=E$3,"R",IF('Master Plan'!$H14=E$3,"A",IF('Master Plan'!$I14=E$3,"C",IF('Master Plan'!$J14=E$3,"I","")))) | F14: =IF('Master Plan'!$G14=F$3,"R",IF('Master Plan'!$H14=F$3,"A",IF('Master Plan'!$I14=F$3,"C",IF('Master Plan'!$J14=F$3,"I","")))) | G14: =IF('Master Plan'!$G14=G$3,"R",IF('Master Plan'!$H14=G$3,"A",IF('Master Plan'!$I14=G$3,"C",IF('Master Plan'!$J14=G$3,"I","")))) | H14: =IF('Master Plan'!$G14=H$3,"R",IF('Master Plan'!$H14=H$3,"A",IF('Master Plan'!$I14=H$3,"C",IF('Master Plan'!$J14=H$3,"I","")))) -> R | I14: =IF('Master Plan'!$G14=I$3,"R",IF('Master Plan'!$H14=I$3,"A",IF('Master Plan'!$I14=I$3,"C",IF('Master Plan'!$J14=I$3,"I","")))) | J14: =IF('Master Plan'!$G14=J$3,"R",IF('Master Plan'!$H14=J$3,"A",IF('Master Plan'!$I14=J$3,"C",IF('Master Plan'!$J14=J$3,"I","")))) | K14: =IF('Master Plan'!$G14=K$3,"R",IF('Master Plan'!$H14=K$3,"A",IF('Master Plan'!$I14=K$3,"C",IF('Master Plan'!$J14=K$3,"I","")))) -> C | L14: =IF('Master Plan'!$G14=L$3,"R",IF('Master Plan'!$H14=L$3,"A",IF('Master Plan'!$I14=L$3,"C",IF('Master Plan'!$J14=L$3,"I","")))) | ... X14: =IF('Master Plan'!$G14=X$3,"R",IF('Master Plan'!$H14=X$3,"A",IF('Master Plan'!$I14=X$3,"C",IF('Master Plan'!$J14=X$3,"I","")))) | Y14: =COUNTIF(E14:X14,"R") -> 1 | Z14: =COUNTIF(E14:X14,"A") -> 0 | AA14: =COUNTIF(E14:X14,"C") -> 1 | AB14: =COUNTIF(E14:X14,"I") -> 1
A15: ='Master Plan'!A15 -> T-011 | B15: ='Master Plan'!B15 -> 2. Planning & Design | C15: ='Master Plan'!E15 -> Permits | D15: ='Master Plan'!N15 -> Not Started | E15: =IF('Master Plan'!$G15=E$3,"R",IF('Master Plan'!$H15=E$3,"A",IF('Master Plan'!$I15=E$3,"C",IF('Master Plan'!$J15=E$3,"I","")))) | F15: =IF('Master Plan'!$G15=F$3,"R",IF('Master Plan'!$H15=F$3,"A",IF('Master Plan'!$I15=F$3,"C",IF('Master Plan'!$J15=F$3,"I","")))) -> I | G15: =IF('Master Plan'!$G15=G$3,"R",IF('Master Plan'!$H15=G$3,"A",IF('Master Plan'!$I15=G$3,"C",IF('Master Plan'!$J15=G$3,"I","")))) | H15: =IF('Master Plan'!$G15=H$3,"R",IF('Master Plan'!$H15=H$3,"A",IF('Master Plan'!$I15=H$3,"C",IF('Master Plan'!$J15=H$3,"I","")))) -> R | I15: =IF('Master Plan'!$G15=I$3,"R",IF('Master Plan'!$H15=I$3,"A",IF('Master Plan'!$I15=I$3,"C",IF('Master Plan'!$J15=I$3,"I","")))) | J15: =IF('Master Plan'!$G15=J$3,"R",IF('Master Plan'!$H15=J$3,"A",IF('Master Plan'!$I15=J$3,"C",IF('Master Plan'!$J15=J$3,"I","")))) | K15: =IF('Master Plan'!$G15=K$3,"R",IF('Master Plan'!$H15=K$3,"A",IF('Master Plan'!$I15=K$3,"C",IF('Master Plan'!$J15=K$3,"I","")))) | L15: =IF('Master Plan'!$G15=L$3,"R",IF('Master Plan'!$H15=L$3,"A",IF('Master Plan'!$I15=L$3,"C",IF('Master Plan'!$J15=L$3,"I","")))) | ... X15: =IF('Master Plan'!$G15=X$3,"R",IF('Master Plan'!$H15=X$3,"A",IF('Master Plan'!$I15=X$3,"C",IF('Master Plan'!$J15=X$3,"I","")))) | Y15: =COUNTIF(E15:X15,"R") -> 1 | Z15: =COUNTIF(E15:X15,"A") -> 0 | AA15: =COUNTIF(E15:X15,"C") -> 1 | AB15: =COUNTIF(E15:X15,"I") -> 1
A16: ='Master Plan'!A16 -> T-012 | B16: ='Master Plan'!B16 -> 2. Planning & Design | C16: ='Master Plan'!E16 -> Process Design | D16: ='Master Plan'!N16 -> Not Started | E16: =IF('Master Plan'!$G16=E$3,"R",IF('Master Plan'!$H16=E$3,"A",IF('Master Plan'!$I16=E$3,"C",IF('Master Plan'!$J16=E$3,"I","")))) | F16: =IF('Master Plan'!$G16=F$3,"R",IF('Master Plan'!$H16=F$3,"A",IF('Master Plan'!$I16=F$3,"C",IF('Master Plan'!$J16=F$3,"I","")))) | G16: =IF('Master Plan'!$G16=G$3,"R",IF('Master Plan'!$H16=G$3,"A",IF('Master Plan'!$I16=G$3,"C",IF('Master Plan'!$J16=G$3,"I","")))) | H16: =IF('Master Plan'!$G16=H$3,"R",IF('Master Plan'!$H16=H$3,"A",IF('Master Plan'!$I16=H$3,"C",IF('Master Plan'!$J16=H$3,"I","")))) | I16: =IF('Master Plan'!$G16=I$3,"R",IF('Master Plan'!$H16=I$3,"A",IF('Master Plan'!$I16=I$3,"C",IF('Master Plan'!$J16=I$3,"I","")))) -> C | J16: =IF('Master Plan'!$G16=J$3,"R",IF('Master Plan'!$H16=J$3,"A",IF('Master Plan'!$I16=J$3,"C",IF('Master Plan'!$J16=J$3,"I","")))) | K16: =IF('Master Plan'!$G16=K$3,"R",IF('Master Plan'!$H16=K$3,"A",IF('Master Plan'!$I16=K$3,"C",IF('Master Plan'!$J16=K$3,"I","")))) | L16: =IF('Master Plan'!$G16=L$3,"R",IF('Master Plan'!$H16=L$3,"A",IF('Master Plan'!$I16=L$3,"C",IF('Master Plan'!$J16=L$3,"I","")))) | ... X16: =IF('Master Plan'!$G16=X$3,"R",IF('Master Plan'!$H16=X$3,"A",IF('Master Plan'!$I16=X$3,"C",IF('Master Plan'!$J16=X$3,"I","")))) | Y16: =COUNTIF(E16:X16,"R") -> 1 | Z16: =COUNTIF(E16:X16,"A") -> 0 | AA16: =COUNTIF(E16:X16,"C") -> 1 | AB16: =COUNTIF(E16:X16,"I") -> 1
... A85: ='Master Plan'!A85 -> T-081 | B85: ='Master Plan'!B85 -> 8. Hypercare & Close | C85: ='Master Plan'!E85 -> Gate 8 Review | D85: ='Master Plan'!N85 -> Not Started | E85: =IF('Master Plan'!$G85=E$3,"R",IF('Master Plan'!$H85=E$3,"A",IF('Master Plan'!$I85=E$3,"C",IF('Master Plan'!$J85=E$3,"I","")))) -> A | F85: =IF('Master Plan'!$G85=F$3,"R",IF('Master Plan'!$H85=F$3,"A",IF('Master Plan'!$I85=F$3,"C",IF('Master Plan'!$J85=F$3,"I","")))) -> R | G85: =IF('Master Plan'!$G85=G$3,"R",IF('Master Plan'!$H85=G$3,"A",IF('Master Plan'!$I85=G$3,"C",IF('Master Plan'!$J85=G$3,"I","")))) | H85: =IF('Master Plan'!$G85=H$3,"R",IF('Master Plan'!$H85=H$3,"A",IF('Master Plan'!$I85=H$3,"C",IF('Master Plan'!$J85=H$3,"I","")))) | I85: =IF('Master Plan'!$G85=I$3,"R",IF('Master Plan'!$H85=I$3,"A",IF('Master Plan'!$I85=I$3,"C",IF('Master Plan'!$J85=I$3,"I","")))) | J85: =IF('Master Plan'!$G85=J$3,"R",IF('Master Plan'!$H85=J$3,"A",IF('Master Plan'!$I85=J$3,"C",IF('Master Plan'!$J85=J$3,"I","")))) | K85: =IF('Master Plan'!$G85=K$3,"R",IF('Master Plan'!$H85=K$3,"A",IF('Master Plan'!$I85=K$3,"C",IF('Master Plan'!$J85=K$3,"I","")))) | L85: =IF('Master Plan'!$G85=L$3,"R",IF('Master Plan'!$H85=L$3,"A",IF('Master Plan'!$I85=L$3,"C",IF('Master Plan'!$J85=L$3,"I","")))) | ... X85: =IF('Master Plan'!$G85=X$3,"R",IF('Master Plan'!$H85=X$3,"A",IF('Master Plan'!$I85=X$3,"C",IF('Master Plan'!$J85=X$3,"I","")))) -> C | Y85: =COUNTIF(E85:X85,"R") -> 1 | Z85: =COUNTIF(E85:X85,"A") -> 1 | AA85: =COUNTIF(E85:X85,"C") -> 1 | AB85: =COUNTIF(E85:X85,"I") -> 1
A86: Assignments per stakeholder | D86: Total R | E86: =COUNTIF(E5:E85,"R") -> 1 | F86: =COUNTIF(F5:F85,"R") -> 14 | G86: =COUNTIF(G5:G85,"R") -> 1 | H86: =COUNTIF(H5:H85,"R") -> 5 | I86: =COUNTIF(I5:I85,"R") -> 1 | J86: =COUNTIF(J5:J85,"R") -> 5 | K86: =COUNTIF(K5:K85,"R") -> 2 | L86: =COUNTIF(L5:L85,"R") -> 4 | ... X86: =COUNTIF(X5:X85,"R") -> 2
D87: Total A | E87: =COUNTIF(E5:E85,"A") -> 14 | F87: =COUNTIF(F5:F85,"A") -> 5 | G87: =COUNTIF(G5:G85,"A") -> 0 | H87: =COUNTIF(H5:H85,"A") -> 0 | I87: =COUNTIF(I5:I85,"A") -> 6 | J87: =COUNTIF(J5:J85,"A") -> 1 | K87: =COUNTIF(K5:K85,"A") -> 5 | L87: =COUNTIF(L5:L85,"A") -> 4 | ... X87: =COUNTIF(X5:X85,"A") -> 0
D88: Total C | E88: =COUNTIF(E5:E85,"C") -> 0 | F88: =COUNTIF(F5:F85,"C") -> 6 | G88: =COUNTIF(G5:G85,"C") -> 2 | H88: =COUNTIF(H5:H85,"C") -> 4 | I88: =COUNTIF(I5:I85,"C") -> 9 | J88: =COUNTIF(J5:J85,"C") -> 14 | K88: =COUNTIF(K5:K85,"C") -> 4 | L88: =COUNTIF(L5:L85,"C") -> 5 | ... X88: =COUNTIF(X5:X85,"C") -> 2
D89: Total I | E89: =COUNTIF(E5:E85,"I") -> 6 | F89: =COUNTIF(F5:F85,"I") -> 8 | G89: =COUNTIF(G5:G85,"I") -> 2 | H89: =COUNTIF(H5:H85,"I") -> 2 | I89: =COUNTIF(I5:I85,"I") -> 10 | J89: =COUNTIF(J5:J85,"I") -> 2 | K89: =COUNTIF(K5:K85,"I") -> 3 | L89: =COUNTIF(L5:L85,"I") -> 2 | ... X89: =COUNTIF(X5:X85,"I") -> 0

Sheet Gate Checklists
A1: Completeness Gate Checklists — a phase cannot close while any item is open
A2: Blue = input. Gate status is calculated. The AI Copilot audits these lists before each gate review and lists gaps for the PM to confirm.
A4: Gate | B4: Checklist Item | C4: Owner (ID) | D4: Linked Task(s) | E4: Status | F4: Evidence / Link | G4: Reviewed By | H4: Review Date | I4: Comments
A5: Gate 1 — Initiation complete | E5: Gate status: | F5: =IF(COUNTIFS(E6:E11,"Open")+COUNTIFS(E6:E11,"In Progress")=0,"PASSED","OPEN — "&(COUNTIFS(E6:E11,"Open")+COUNTIFS(E6:E11,"In Progress"))&" item(s)") -> PASSED | G5: =COUNTIFS(E6:E11,"Complete")+COUNTIFS(E6:E11,"N/A")&" / "&COUNTA(B6:B11)&" done" -> 6 / 6 done
A6: G1 | B6: Project charter approved by sponsor | C6: SH-02 | E6: Complete
A7: G1 | B7: Budget baseline approved and funding released | C7: SH-02 | E7: Complete
A8: G1 | B8: Stakeholder register complete with escalation paths | C8: SH-02 | E8: Complete
A9: G1 | B9: Steering committee cadence and RAID log established | C9: SH-02 | E9: Complete
A10: G1 | B10: Gate checklists and templates loaded into PM tool / AI Copilot | C10: SH-02 | E10: Complete
A11: G1 | B11: Vendor shortlist and SOW status confirmed | C11: SH-02 | E11: Complete
A13: Gate 2 — Planning & design complete | E13: Gate status: | F13: =IF(COUNTIFS(E14:E22,"Open")+COUNTIFS(E14:E22,"In Progress")=0,"PASSED","OPEN — "&(COUNTIFS(E14:E22,"Open")+COUNTIFS(E14:E22,"In Progress"))&" item(s)") -> OPEN — 1 item(s) | G13: =COUNTIFS(E14:E22,"Complete")+COUNTIFS(E14:E22,"N/A")&" / "&COUNTA(B14:B22)&" done" -> 8 / 9 done
A14: G2 | B14: Integrated master plan baselined; critical path identified | C14: SH-02 | E14: Complete
A15: G2 | B15: RAID baseline reviewed; every item has owner and due date | C15: SH-02 | E15: Complete
A16: G2 | B16: Facility design and permits submitted | C16: SH-02 | E16: Complete
A17: G2 | B17: WMS functional and technical design signed off | C17: SH-02 | E17: Complete
A18: G2 | B18: Automation design and throughput model approved | C18: SH-02 | E18: Complete
A19: G2 | B19: Interface catalogue and data migration strategy approved | C19: SH-02 | E19: Complete
A20: G2 | B20: Test strategy approved with exit criteria | C20: SH-02 | E20: Complete
A21: G2 | B21: Vendor contracts executed with milestone schedule | C21: SH-02 | E21: Complete
A22: G2 | B22: Change and training plan approved | C22: SH-02 | E22: Open
A24: Gate 3 — Build complete | E24: Gate status: | F24: =IF(COUNTIFS(E25:E32,"Open")+COUNTIFS(E25:E32,"In Progress")=0,"PASSED","OPEN — "&(COUNTIFS(E25:E32,"Open")+COUNTIFS(E25:E32,"In Progress"))&" item(s)") -> OPEN — 8 item(s) | G24: =COUNTIFS(E25:E32,"Complete")+COUNTIFS(E25:E32,"N/A")&" / "&COUNTA(B25:B32)&" done" -> 0 / 8 done
A25: G3 | B25: WMS configuration and customisations complete and unit tested | C25: SH-02 | E25: Open
A26: G3 | B26: All interfaces developed and unit tested | C26: SH-02 | E26: Open
A27: G3 | B27: Mock data load 1 executed with reconciliation | C27: SH-02 | E27: Open
A28: G3 | B28: Equipment manufactured and shipping confirmed | C28: SH-02 | E28: Open
A29: G3 | B29: WCS developed; emulation model available | C29: SH-02 | E29: Open
A30: G3 | B30: Construction on schedule; no open permit issues | C30: SH-02 | E30: Open
A31: G3 | B31: SOPs drafted for every process | C31: SH-02 | E31: Open
A32: G3 | B32: Capex within tolerance | C32: SH-02 | E32: Open
A34: Gate 4 — Site ready | E34: Gate status: | F34: =IF(COUNTIFS(E35:E40,"Open")+COUNTIFS(E35:E40,"In Progress")=0,"PASSED","OPEN — "&(COUNTIFS(E35:E40,"Open")+COUNTIFS(E35:E40,"In Progress"))&" item(s)") -> OPEN — 6 item(s) | G34: =COUNTIFS(E35:E40,"Complete")+COUNTIFS(E35:E40,"N/A")&" / "&COUNTA(B35:B40)&" done" -> 0 / 6 done
A35: G4 | B35: Racking, mezzanine and dock equipment installed | C35: SH-02 | E35: Open
A36: G4 | B36: MHE installed and dry-commissioned | C36: SH-02 | E36: Open
A37: G4 | B37: Safety inspections passed; certificate of occupancy obtained | C37: SH-02 | E37: Open
A38: G4 | B38: Site network, RF devices and printers live | C38: SH-02 | E38: Open
A39: G4 | B39: Supervisors hired and onboarded | C39: SH-02 | E39: Open
A40: G4 | B40: Yard and dock scheduling ready | C40: SH-02 | E40: Open
A42: Gate 5 — Testing complete | E42: Gate status: | F42: =IF(COUNTIFS(E43:E49,"Open")+COUNTIFS(E43:E49,"In Progress")=0,"PASSED","OPEN — "&(COUNTIFS(E43:E49,"Open")+COUNTIFS(E43:E49,"In Progress"))&" item(s)") -> OPEN — 7 item(s) | G42: =COUNTIFS(E43:E49,"Complete")+COUNTIFS(E43:E49,"N/A")&" / "&COUNTA(B43:B49)&" done" -> 0 / 7 done
A43: G5 | B43: SIT exit criteria met | C43: SH-02 | E43: Open
A44: G5 | B44: Performance test passed at peak volume | C44: SH-02 | E44: Open
A45: G5 | B45: Throughput acceptance test ≥ 95% of design rate | C45: SH-02 | E45: Open
A46: G5 | B46: UAT signed off by operations | C46: SH-02 | E46: Open
A47: G5 | B47: Carrier and supplier EDI tests passed | C47: SH-02 | E47: Open
A48: G5 | B48: Zero open Sev-1 defects; Sev-2 plan agreed | C48: SH-02 | E48: Open
A49: G5 | B49: Mock data load 2 reconciled | C49: SH-02 | E49: Open
A51: Gate 6 — People ready | E51: Gate status: | F51: =IF(COUNTIFS(E52:E56,"Open")+COUNTIFS(E52:E56,"In Progress")=0,"PASSED","OPEN — "&(COUNTIFS(E52:E56,"Open")+COUNTIFS(E52:E56,"In Progress"))&" item(s)") -> OPEN — 5 item(s) | G51: =COUNTIFS(E52:E56,"Complete")+COUNTIFS(E52:E56,"N/A")&" / "&COUNTA(B52:B56)&" done" -> 0 / 5 done
A52: G6 | B52: Training content complete for all roles | C52: SH-02 | E52: Open
A53: G6 | B53: Super-users certified per process per shift | C53: SH-02 | E53: Open
A54: G6 | B54: 100% of go-live associates trained and certified | C54: SH-02 | E54: Open
A55: G6 | B55: Operational dress rehearsal passed | C55: SH-02 | E55: Open
A56: G6 | B56: Go-live communications issued to stakeholders, suppliers and carriers | C56: SH-02 | E56: Open
A58: Gate 7 — Go / No-Go and go-live | E58: Gate status: | F58: =IF(COUNTIFS(E59:E65,"Open")+COUNTIFS(E59:E65,"In Progress")=0,"PASSED","OPEN — "&(COUNTIFS(E59:E65,"Open")+COUNTIFS(E59:E65,"In Progress"))&" item(s)") -> OPEN — 7 item(s) | G58: =COUNTIFS(E59:E65,"Complete")+COUNTIFS(E59:E65,"N/A")&" / "&COUNTA(B59:B65)&" done" -> 0 / 7 done
A59: G7 | B59: Cutover runbook approved with rollback plan | C59: SH-02 | E59: Open
A60: G7 | B60: Cutover rehearsal completed within window | C60: SH-02 | E60: Open
A61: G7 | B61: Readiness assessment green across all workstreams | C61: SH-02 | E61: Open
A62: G7 | B62: Production data load reconciled and signed off | C62: SH-02 | E62: Open
A63: G7 | B63: Production code deployed and smoke tested | C63: SH-02 | E63: Open
A64: G7 | B64: Command center and escalation rota active | C64: SH-02 | E64: Open
A65: G7 | B65: First inbound receipt and outbound shipment executed | C65: SH-02 | E65: Open
A67: Gate 8 — Hypercare exit and close | E67: Gate status: | F67: =IF(COUNTIFS(E68:E74,"Open")+COUNTIFS(E68:E74,"In Progress")=0,"PASSED","OPEN — "&(COUNTIFS(E68:E74,"Open")+COUNTIFS(E68:E74,"In Progress"))&" item(s)") -> OPEN — 7 item(s) | G67: =COUNTIFS(E68:E74,"Complete")+COUNTIFS(E68:E74,"N/A")&" / "&COUNTA(B68:B74)&" done" -> 0 / 7 done
A68: G8 | B68: Hypercare exit criteria met (defects, throughput, inventory accuracy) | C68: SH-02 | E68: Open
A69: G8 | B69: Volume ramp on plan | C69: SH-02 | E69: Open
A70: G8 | B70: Financial close and benefits baseline complete | C70: SH-02 | E70: Open
A71: G8 | B71: Vendor acceptance certificates issued; warranties started | C71: SH-02 | E71: Open
A72: G8 | B72: Handover to run organisation complete | C72: SH-02 | E72: Open
A73: G8 | B73: Lessons learned published; WBS / RAID / checklist templates updated | C73: SH-02 | E73: Open
A74: G8 | B74: All actions closed; project archived | C74: SH-02 | E74: Open

Sheet RAID Log
A1: RAID Log — Risks, Assumptions, Issues, Dependencies
A2: Blue = input. Score = Probability × Impact (1–5 each). The AI Copilot proposes new entries from tasks, emails and meetings; the PM confirms them here.
A4: RAID ID | B4: Type | C4: Description | D4: Linked Task | E4: Workstream | F4: Owner (ID) | G4: Raised On | H4: Probability (1-5) | I4: Impact (1-5) | J4: Score | K4: Severity | L4: Mitigation / Response | M4: Due Date | N4: Status | O4: Days Overdue | P4: Source | Q4: Last Updated
A5: R-001 | B5: Risk | C5: MHE vendor manufacturing lead time may slip due to component shortages | D5: T-031 | E5: Automation (MHE) | F5: SH-07 | G5: 46328 | H5: 3 | I5: 5 | J5: =IF(OR(H5="",I5=""),"",H5*I5) -> 15 | K5: =IF(J5="","",IF(J5>=15,"High",IF(J5>=8,"Medium","Low"))) -> High | L5: Weekly vendor milestone review; identify alternate suppliers for long-lead components; 2-week buffer in plan | M5: 46384 | N5: Open | O5: =IF(OR(N5="Closed",N5="Mitigated",N5="Accepted",M5=""),0,MAX(0,TODAY()-M5)) -> 0 | P5: Vendor status email | Q5: 46321
A6: R-002 | B6: Risk | C6: Permit approval delays could push construction start | D6: T-011 | E6: Site Readiness | F6: SH-04 | G6: 46335 | H6: 2 | I6: 4 | J6: =IF(OR(H6="",I6=""),"",H6*I6) -> 8 | K6: =IF(J6="","",IF(J6>=15,"High",IF(J6>=8,"Medium","Low"))) -> Medium | L6: Pre-submission meeting with authority; expediter engaged | M6: 46356 | N6: Open | O6: =IF(OR(N6="Closed",N6="Mitigated",N6="Accepted",M6=""),0,MAX(0,TODAY()-M6)) -> 0 | P6: Steering committee | Q6: 46321
A7: A-003 | B7: Assumption | C7: ERP will expose standard APIs for inventory sync without customisation | D7: T-016 | E7: Integration & Data | F7: SH-08 | G7: 46342 | H7: 2 | I7: 3 | J7: =IF(OR(H7="",I7=""),"",H7*I7) -> 6 | K7: =IF(J7="","",IF(J7>=15,"High",IF(J7>=8,"Medium","Low"))) -> Low | L7: Validate in interface design workshop; raise issue if custom work needed | M7: 46363 | N7: Open | O7: =IF(OR(N7="Closed",N7="Mitigated",N7="Accepted",M7=""),0,MAX(0,TODAY()-M7)) -> 0 | P7: Design workshop | Q7: 46321
A8: D-004 | B8: Dependency | C8: WMS SIT depends on WCS emulation model delivery from vendor | D8: T-050 | E8: Testing | F8: SH-10 | G8: 46356 | H8: 3 | I8: 4 | J8: =IF(OR(H8="",I8=""),"",H8*I8) -> 12 | K8: =IF(J8="","",IF(J8>=15,"High",IF(J8>=8,"Medium","Low"))) -> Medium | L8: Contractual milestone; emulation delivery tracked as T-032; fallback manual stubs | M8: 46482 | N8: Open | O8: =IF(OR(N8="Closed",N8="Mitigated",N8="Accepted",M8=""),0,MAX(0,TODAY()-M8)) -> 0 | P8: AI Copilot — dependency check | Q8: 46321
A9: I-005 | B9: Issue | C9: Wi-Fi survey identified coverage gaps in mezzanine area | D9: T-019 | E9: Infrastructure | F9: SH-18 | G9: 46349 | H9: 5 | I9: 3 | J9: =IF(OR(H9="",I9=""),"",H9*I9) -> 15 | K9: =IF(J9="","",IF(J9>=15,"High",IF(J9>=8,"Medium","Low"))) -> High | L9: Add access points to design; revise infrastructure budget | M9: 46363 | N9: In Progress | O9: =IF(OR(N9="Closed",N9="Mitigated",N9="Accepted",M9=""),0,MAX(0,TODAY()-M9)) -> 0 | P9: Site survey report | Q9: 46321
A10: R-006 | B10: Risk | C10: Local labour market may not support hiring plan for go-live headcount | D10: T-061 | E10: Operations & Staffing | F10: SH-11 | G10: 46342 | H10: 3 | I10: 4 | J10: =IF(OR(H10="",I10=""),"",H10*I10) -> 12 | K10: =IF(J10="","",IF(J10>=15,"High",IF(J10>=8,"Medium","Low"))) -> Medium | L10: Start recruiting 4 weeks earlier; staffing agency backup; referral programme | M10: 46510 | N10: Open | O10: =IF(OR(N10="Closed",N10="Mitigated",N10="Accepted",M10=""),0,MAX(0,TODAY()-M10)) -> 0 | P10: Hiring plan review | Q10: 46321
A11: D-007 | B11: Dependency | C11: Carrier EDI testing requires carriers to have TMS lanes configured first | D11: T-056 | E11: Transportation | F11: SH-12 | G11: 46363 | H11: 2 | I11: 3 | J11: =IF(OR(H11="",I11=""),"",H11*I11) -> 6 | K11: =IF(J11="","",IF(J11>=15,"High",IF(J11>=8,"Medium","Low"))) -> Low | L11: Sequence T-037 before T-056; confirm carrier readiness monthly | M11: 46552 | N11: Open | O11: =IF(OR(N11="Closed",N11="Mitigated",N11="Accepted",M11=""),0,MAX(0,TODAY()-M11)) -> 0 | P11: AI Copilot — meeting notes | Q11: 46321

Sheet Action Log
A1: Action Log — decisions and follow-ups from meetings (AI Copilot extracts; PM confirms)
A4: Action ID | B4: Action | C4: Source Meeting / Date | D4: Owner (ID) | E4: Linked Task | F4: Due Date | G4: Status | H4: Days Overdue | I4: Closed On | J4: Notes
A5: A-001 | B5: Confirm alternate supplier options for conveyor drives | C5: Vendor review 20-Oct-26 | D5: SH-13 | E5: T-031 | F5: 46328 | G5: Open | H5: =IF(OR(G5="Complete",G5="Cancelled",F5=""),0,MAX(0,TODAY()-F5)) -> 0
A6: A-002 | B6: Circulate revised Wi-Fi design with additional access points | C6: Infra design 22-Oct-26 | D6: SH-18 | E6: T-019 | F6: 46324 | G6: In Progress | H6: =IF(OR(G6="Complete",G6="Cancelled",F6=""),0,MAX(0,TODAY()-F6)) -> 0
A7: A-003 | B7: Book pre-submission meeting with permitting authority | C7: Steering committee 23-Oct-26 | D7: SH-04 | E7: T-011 | F7: 46325 | G7: Complete | H7: =IF(OR(G7="Complete",G7="Cancelled",F7=""),0,MAX(0,TODAY()-F7)) -> 0 | I7: 46323
